Workbook

Sheet Comparision
A2: Sinario | B2: Initial cash required | C2: Project Profit | D2: JV Share | E2: Developer
A3: Rental Approach @ 70% LVR | B3: ='7 Yr Valuation & Cashflow'!L8 -> 1199892 | C3: ='7 Yr Valuation & Cashflow'!D22 -> 539448 | D3: ='7 Yr Valuation & Cashflow'!M15 -> 0.60352941 | E3: =+(100%-D3)*C3 -> 213875.27 | F3: 1 Yr
A4: Sell both @ 70% LVR | B4: ='2 x Land Sales@ 70LVR'!F27 -> 1164104 | C4: ='2 x Land Sales@ 70LVR'!B90 -> 359375.8 | D4: ='2 x Land Sales@ 70LVR'!D59 -> 0.50676471 | E4: =+(100%-D4)*C4 -> 177256.83
A5: Sell both @ 80% LVR | B5: ='2 x Land Sales@ 80 LVR'!F28 -> 942047.6 | C5: ='2 x Land Sales@ 80 LVR'!B75 -> 271875 | D5: ='2 x Land Sales@ 80 LVR'!E50 -> 0.42352941 | E5: =+(100%-D5)*C5 -> 156727.94
A6: Sell 1 and hold 1 @ 70% LVR | B6: ='Sell 1 hold 1 at 70% LVR'!F27 -> 1170852 | C6: ='Sell 1 hold 1 at 70% LVR'!D59 -> 397764.08 | D6: 0.6 | E6: =+(100%-D6)*C6 -> 159105.63 | F6: 1 Yr
A13: Quotes
A15: Demo (incl GST) | B15: A1 | C15: Nu Tec | D15: AMW
A17: Demo 94-96 | B17: 76400 | C17: =30000*1.1 -> 33000
A18: Demo 92 | D18: 36300
A19: Asbestos Certificate | C19: =350*1.1 -> 385 | D19: 0
A20: Abolishment of Electricity 94-96 | B20: =550*10 -> 5500 | C20: =550*10 -> 5500 | D20: =550*10 -> 5500
A21: Abolishment of Gas | B21: =770*10 -> 7700 | C21: =252*10 -> 2520 | D21: =252*10 -> 2520
A22: Temp Fencing | B22: 880 | D22: 600
A23: Sewer Caping | B23: 1540 | C23: =1200*1.1 -> 1320
A24: Stumping | C24: =250*1.1 -> 275
A25: Admin Fee | C25: =250*1.1 -> 275
A28: Total | B28: =SUM(B17:B27) -> 92020 | C28: =SUM(C17:C27) -> 43275
A29: Deposit | C29: 0.2 | D29: 0.3
A30: Asbestos Included | B30: Yes | C30: Yes | D30: No
A32: Temp Fence Dimension | B32: Front | C32: Side
A33: 92 | B33: 15.3
A34: 94 | B34: 14.8
A35: 96 | B35: 15.3
B36: =SUM(B33:B35) -> 45.4

Sheet Capital Stack
A1: Yr # | B1: 1 | I1: Amt | J1: % | K1: Share per 100% | L1: val
B2: 2026 | H2: Stage 1 Capital Raising | I2: 800000 | J2: 0.42 | K2: =(100000/I2)*J2 -> 0.0525 | L2: =(100%/J2)*I2 -> 1904761.9
A3: Property Valuation | B3: ='7 Yr Valuation & Cashflow'!C5 -> 2760000 | H3: Stage 2 Capital Raising | I3: 450000 | J3: 0.18 | K3: =(100000/I3)*J3 -> 0.04 | L3: =(100%/J3)*I3 -> 2500000
A4: StampDuty | B4: ='7 Yr Valuation & Cashflow'!C7 -> 165600 | I4: =SUM(I2:I3) -> 1250000 | J4: =SUM(J2:J3) -> 0.6
A5: Closing costs + Due Dilligence | B5: ='7 Yr Valuation & Cashflow'!C8 -> 15000
A6: Finders fee | B6: ='7 Yr Valuation & Cashflow'!C9 -> 40000 | H6: Stage 2 Formaula
A7: Finance cost | B7: ='Senior Funding Model'!D20 -> 22252 | H7: Capital contribution | I7: =200000 -> 200000
A8: Operating Reserve & Repairs | B8: ='Sell 1 hold 1 at 70% LVR'!C26 -> 129040 | H8: % share
A9: Total Cost | B9: =SUM(B3:B8) -> 3131892
A11: Market Valuation (MV) | B11: 2760000 | H11: Graph
A12: LVR | B12: 0.7 | H12: Capital Stack | I12: Amount | J12: Stack | R12: 2950000
A13: Senior Loan | B13: =+B11*B12 -> 1932000 | H13: Senior Loan (70% LVR) | I13: =B13 -> 1932000 | J13: =+I13 -> 1932000 | R13: -100000 | S13: Deposit
A14: Cash required to settle | B14: =$B$9-(B11*B12) -> 1199892 | H14: Round 1 Capital Raising | I14: =800000 -> 800000 | J14: =+J13+I14 -> 2732000 | R14: -1932000
H15: Round 2 Capital Raising | I15: 200000 | J15: =+J14+I15 -> 2932000 | R15: =SUM(R12:R14) -> 918000
A16: Investors | B16: Amt Contributed | C16: % Interest in the deal | H16: Total Capital Stack
A17: Vish Associates Pty Ltd (ABN 56 647 166 112) ATF Narayan Family Wealth Trust | B17: 600000 | C17: =((400000/850000)*0.45)+(200000/450000)*0.18 -> 0.29176471
A18: Sharath Reddy Kancharla | B18: 195000 | C18: =(B18/850000)*0.45 -> 0.10323529
A19: ARVR Holdings PtyLtd ATF ARVR Family Trust | B19: 200000 | C19: =(B19/850000)*0.45 -> 0.10588235
A20: Krishna's Bucket Company | C20: =100%-C17-C18-C19 -> 0.49911765 | F20: Investor Payments
A21: Total | B21: =SUM(B17:B20) -> 995000 | C21: =SUM(C17:C20) -> 1 | F21: Date | G21: Vivek | H21: Sharath | I21: Vijay | J21: Ramakanth (loan)
F22: 45721 | H22: 10000
A23: Money Parter (Loan) | F23: 45729 | H23: 60000
A24: Ramakanth | B24: 150000 | F24: 45776 | G24: 35000
A25: Total Cash Raised | B25: =B21+B24 -> 1145000 | F25: 45777 | G25: 35000
F26: 45982 | G26: 25000
A27: Cash require | F27: 46003 | G27: 95000
A28: Homesly expenses | B28: 15000 | F28: 46006 | G28: 95000
A29: Equity 30% | B29: =B3*30% -> 828000 | F29: 46007 | G29: 55000
A30: Stamp Duty | B30: =B4 -> 165600 | F30: 46008 | G30: 50000
A31: Finders Fee | B31: =B6 -> 40000 | F31: 46016 | H31: 40000
A32: Finance Cost | B32: =B7 -> 22252 | F32: 46018 | H32: 40000 | I32: 3000
A33: Closing costs | B33: =B5 -> 15000 | F33: 46019 | H33: 50000
B34: =SUM(B28:B33) -> 1085852 | F34: 46020 | I34: =47000+50000+50000 -> 147000 | J34: 100000
A35: Deficit / Surplus | B35: =B25-B34 -> 59148 | F35: 46021 | I35: 50000 | J35: 50000
F36: 45662 | G36: 97000
F37: 45663 | G37: 100000
F38: 45695
F39: Paid to date | G39: =SUM(G22:G37) -> 587000 | H39: =SUM(H22:H37) -> 200000 | I39: =SUM(I22:I37) -> 200000 | J39: =SUM(J22:J37) -> 150000 | K39: =SUM(G39:J39) -> 1137000
F40: Committed | G40: 600000 | H40: 200000 | I40: 200000 | J40: 150000 | K40: =SUM(G40:J40) -> 1150000
F41: Outstanding | G41: =G40-G39 -> 13000 | H41: =H40-H39 -> 0 | I41: =I40-I39 -> 0 | J41: =J40-J39 -> 0 | K41: =SUM(G41:J41) -> 13000
F43: Total paid | G43: =G39+H39+I39+J39 -> 1137000
F44: Still to pay | G44: =SUM(G41:J41) -> 13000
F45: Total expected | G45: =SUM(G43:G44) -> 1150000

Sheet cashflow
A1: PROJECT PROGRAMME | B1: Jan | C1: Feb | D1: Mar | E1: Apr | F1: May | G1: Jun | H1: Jul | I1: Aug | J1: Sep | K1: Oct | L1: Nov | M1: Dec | N1: TOTAL
A2: MONTH | B2: 1 | C2: 2 | D2: 3 | E2: 4 | F2: 5 | G2: 6 | H2: 7 | I2: 8 | J2: 9 | K2: 10 | L2: 11 | M2: 12
A3: Opening Balance | B3: ='[1]Cashflow Summary'!$O$68 -> 22229.31 | C3: =B41 -> 34922.72 | D3: =C41 -> 62971.52 | E3: =D41 -> 48601.32 | F3: =E41 -> 50245.912 | G3: =F41 -> 47890.503 | H3: =G41 -> 1357815.1 | I3: =H41 -> 1357780.1 | J3: =I41 -> 1357745.1 | ... M3: =L41 -> 1357290.1
A4: Investment - Vivek | B4: =600000-70000-25000+200000 -> 705000 | N4: =SUM(B4:M4) -> 705000
A5: Invetsment from Sharath | B5: =195000-70000 -> 125000 | N5: =SUM(B5:M5) -> 125000
N6: =SUM(B6:M6) -> 0
A7: Loan from Ramakanth | B7: 150000 | C7: -50000 | N7: =SUM(B7:M7) -> 100000
A8: Bank | B8: =2760000*70% -> 1932000
A9: Private Loan- Vijay | N9: =SUM(B9:M9) -> 0
A10: Deposit Early Release | C10: =1765000*10% -> 176500
A11: Sale 96 | D11: =1765000-C10 -> 1588500 | G11: 1800000
N12: =SUM(B12:M12) -> 0
A13: Total Income | B13: =SUM(B4:B12) -> 2912000 | C13: =SUM(C4:C12) -> 126500 | D13: =SUM(D4:D12) -> 1588500 | E13: =SUM(E4:E12) -> 0 | F13: =SUM(F4:F12) -> 0 | G13: =SUM(G4:G12) -> 1800000 | H13: =SUM(H4:H12) -> 0 | I13: =SUM(I4:I12) -> 0 | ... N13: =SUM(N4:N12) -> 930000
A14: Loan repaymnet | D14: =D11-D38+D7-10000 -> 1478500 | G14: =F44 -> 453500 | N14: =SUM(B14:M14) -> 1932000
A15: Loan Interest | B15: =$B$8*6.18%/12 -> 9949.8 | C15: =$B$8*6.18%/12 -> 9949.8 | D15: =$B$8*6.18%/12 -> 9949.8
A16: Purchase cost | B16: 2660000 | N16: =SUM(B16:M16) -> 2660000
A17: Stamp Duty+adjutsments | B17: =159400+5743.09 -> 165143.09 | N17: =SUM(B17:M17) -> 165143.09 | Q17: =150000*15%/12 -> 1875
A18: Closing cost conveyencer & adjustment | B18: =4780 -> 4780 | D18: 2500 | G18: 3500 | N18: =SUM(B18:M18) -> 10780
A19: Title Office & PEXA | B19: =3736.7+200 -> 3936.7
A20: Funding Cost | B20: =+B8*0.6% -> 11592 | N20: =SUM(B20:M20) -> 11592
A21: Audrey | B21: 11500 | N21: =SUM(B21:M21) -> 11500
A22: Demo | B22: 6600 | C22: =33000-B22 -> 26400 | N22: =SUM(C22:M22) -> 26400
A23: Homesly - Reiumbursement | B23: 13000 | N23: =SUM(B23:M23) -> 13000
A24: Water & Drainage | C24: 25000 | N24: =SUM(C24:M24) -> 25000
A25: Tree permit | B25: =350+800 -> 1150
A26: Gas Abolisgment | B26: =242*10 -> 2420 | N26: =SUM(B26:M26) -> 2420
A27: Electricty Aboloshment | B27: 3000
A28: Sewer PIC` | B28: 250
A29: PIC fire hydrand capping | B29: 750
A30: Interest Payments | C30: =(B44*6.14%)/12 -> 9885.4 | D30: =(C44*6.14%)/12 -> 9885.4 | E30: =(D44*6.14%)/12 -> 2320.4083 | F30: =(E44*6.14%)/12 -> 2320.4083 | G30: =(F44*6.14%)/12 -> 2320.4083 | H30: =(G44*6.14%)/12 -> 0 | I30: =(H44*6.14%)/12 -> 0 | J30: =(I44*6.14%)/12 -> 0 | ... M30: =(L44*6.14%)/12 -> 0 | N30: =SUM(B30:M30) -> 26732.025
A31: Council Rates | G31: 3000 | N31: =SUM(C31:M31) -> 3000
A32: Insurance | B32: 5200 | E32: -4000
A33: MISC | D33: 2000 | N33: =SUM(C33:M33) -> 2000
A34: Sales commission | C34: =1765000*1.54% -> 27181 | D34: =D10*1.54% -> 0 | E34: =E10*1.54% -> 0 | F34: =F10*1.54% -> 0 | G34: =G11*1.54% -> 27720 | N34: =SUM(B34:M34) -> 54901
A35: Land Tax | B35: 0 | N35: =SUM(B35:M35) -> 0
A36: ASIC | L36: 350 | N36: =SUM(M36:M36) -> 0
A37: Xero Fee | B37: 35 | C37: 35 | D37: 35 | E37: 35 | F37: 35 | G37: 35 | H37: 35 | I37: 35 | J37: 35 | K37: 35 | L37: 35 | M37: 35 | N37: =SUM(B37:M37) -> 420
A38: Profit distribution | D38: 100000
A39: Total Expenses | B39: =SUM(B14:B38) -> 2899306.6 | C39: =SUM(C14:C38) -> 98451.2 | D39: =SUM(D14:D38) -> 1602870.2 | E39: =SUM(E14:E38) -> -1644.5917 | F39: =SUM(F14:F38) -> 2355.4083 | G39: =SUM(G14:G38) -> 490075.41 | H39: =SUM(H14:H38) -> 35 | I39: =SUM(I14:I38) -> 35 | ... N39: =SUM(N14:N38) -> 4944888.1
A40: Net Cash flow | B40: =+B13-B39 -> 12693.41 | C40: =+C13-C39 -> 28048.8 | D40: =+D13-D39 -> -14370.2 | E40: =+E13-E39 -> 1644.5917 | F40: =+F13-F39 -> -2355.4083 | G40: =+G13-G39 -> 1309924.6 | H40: =+H13-H39 -> -35 | I40: =+I13-I39 -> -35 | ... M40: =+M13-M39 -> -35 | N40: =SUM(B40:M40) -> 1335025.8
A41: Cash at hand @ EOM | B41: =B3+B40 -> 34922.72 | C41: =C3+C40 -> 62971.52 | D41: =D3+D40 -> 48601.32 | E41: =E3+E40 -> 50245.912 | F41: =F3+F40 -> 47890.503 | G41: =G3+G40 -> 1357815.1 | H41: =H3+H40 -> 1357780.1 | I41: =I3+I40 -> 1357745.1 | ... M41: =M3+M40 -> 1357255.1 | N41: =SUM(B41:M41) -> 9747902.6
A44: Loan Balance | B44: =B8-B14 -> 1932000 | C44: =B44-C14 -> 1932000 | D44: =C44-D14 -> 453500 | E44: =D44-E14 -> 453500 | F44: =E44-F14 -> 453500 | G44: =F44-G14 -> 0 | H44: =G44-H14 -> 0 | I44: =H44-I14 -> 0 | J44: =I44-J14 -> 0 | ... M44: =L44-M14 -> 0
A45: Interest rate | B45: 0.0614
A46: Application Fee | B46: 0.006
O51: …000.
O57: 0

Sheet 2 x Land Sales@ 70LVR
A1: Feasibility | F1: Money Partners | G1: Loan# | H1: Amt | I1: Month Loaned | J1: No. of Month | K1: Interest rate | L1: Interest | M1: Total Amt
A2: Size of each unit | B2: Sqs | C2: 0 | F2: Sharath | G2: 1 | H2: 70000 | I2: 45717 | J2: 15 | K2: 0.15 | L2: =(J2/12)*(H2*K2) -> 13125 | AA2: Settlement
A3: Total Build area in Sqm | B3: Sqm | C3: =+C2*9.29*C5 -> 0 | G3: 2 | H3: =200000-H2 -> 130000 | I3: 45992 | J3: 5 | K3: 0.15 | L3: =(J3/12)*(H3*K3) -> 8125 | M3: =SUM(L2:L3) -> 21250 | AA3: May
A4: Land area in sqm | C4: 1295 | G4: Total | H4: =SUM(H2:H3) -> 200000
A5: No of Dwellings | C5: 2 | E5: Sell per Sq M
A6: Avg Dwellings sell price | B6: 2430 | C6: =+(1765000+1775000)/2 -> 1770000 | E6: =C8/C4 -> 2733.5907 | F6: Vivek | G6: 1 | H6: 70000 | I6: 45748 | J6: 15 | K6: 0.15 | L6: =(J6/12)*(H6*K6) -> 13125
G7: 2 | H7: 100000 | I7: 46023 | J7: 5 | K7: 0.15 | L7: =(J7/12)*(H7*K7) -> 6250
A8: Total Sales | C8: =C6*C5+C7 -> 3540000 | G8: 3 | H8: =600000-H7-H6 -> 430000 | I8: 46023 | J8: 5 | K8: 0.15 | L8: =(J8/12)*(H8*K8) -> 26875 | M8: =SUM(L6:L8) -> 46250
A9: GST on margin scheme | F9: Vijay
A10: Total Revenue | B10: =C10/C10 -> 1 | C10: =+C8+C9 -> 3540000 | G10: Total | H10: =SUM(H6:H8) -> 600000
A11: All costs are GST exclusive | E11: Cost per Sqm | F11: Total Capital | H11: =+H4+H10 -> 800000
A12: Purchase price | B12: =+C12/C10 -> 0.77966102 | C12: 2760000 | E12: =+C12/C4 -> 2131.2741
A13: Stamp duty + buy in Fees | B13: 0.06 | C13: =(C12+C11)*B13 -> 165600 | F13: Ramakanth | G13: 1 | H13: 150000 | I13: 46023 | J13: 5 | K13: 0.15 | L13: =(J13/12)*(H13*K13) -> 9375 | M13: =+L13 -> 9375
A14: Finders Fee | C14: 40000 | F14: Investor 5 | G14: 1 | H14: 250000 | I14: 46023 | J14: 5 | K14: 0.15 | L14: =(J14/12)*(H14*K14) -> 15625 | M14: =+L14 -> 15625
A15: Accounting & Legals | C15: 13000
A16: Funding cost establishment cost | C16: ='Senior Funding Model'!D20 -> 22252
A17: Acquisition cost | B17: =C17/C10 -> 0.84769831 | C17: =SUM(C11:C16) -> 3000852 | F17: Capital amt | H17: =+H11+H13+H14 -> 1200000 | K17: Total Interest | L17: =SUM(L2:L16) -> 92500
A18: Due Dilligence | B18: 0.33 | C18: 0 | F18: Shortfall | H18: =F27-H17 -> -35896
A19: Utilities | B19: 0.01 | C19: 25000 | F19: Senior Debt | G19: 1 | H19: =E27 -> 1932000 | I19: 46023 | J19: 3 | K19: 0.0614 | L19: =(J19/12)*(H19*K19) -> 29656.2
B20: 0.008
A21: Marketing & selling cost | B21: 0.0154 | C21: =$C$10*B21 -> 54516 | F21: Total | H21: =H19+H17 -> 3132000 | J21: Total Funding Cost | L21: =+L19+L17 -> 122156.2
A22: Holding Cost | C22: 5000
A23: Demo | C23: =+(30000*1.1)+10000 -> 43000
A24: Misc cost | F24: Net Cashflow
A25: Total Development Cost | B25: =C25/C10 -> 0.036021469 | C25: =SUM(C18:C24) -> 127516 | R25: Burn Rate | T25: Amt | U25: Rate | V25: Per month
A26: Total Project Cost before funding | C26: =C17+C25 -> 3128368 | E26: Loan | F26: Cash required | R26: Senior Debt | T26: =H19 -> 1932000 | U26: =K19 -> 0.0614 | V26: =T26*U26/12 -> 9885.4
A27: Profit Before Funding cost | B27: =+C27/C26 -> 0.13158043 | C27: =+C10-C26 -> 411632 | E27: =C12*70% -> 1932000 | F27: =+C17-E27+C19+C23+C22+C16 -> 1164104 | R27: Private | T27: 1000000 | U27: 0.15 | V27: =U27*T27/12 -> 12500
A28: Funding Cost w/ money partners | B28: =+C28/C8 -> 0.034507401 | C28: =L21 -> 122156.2 | T28: Total | V28: =SUM(V26:V27) -> 22385.4
A29: JV Partners cost | B29: =+C29/C8 -> 0.0624718 | C29: =+B92-B87 -> 221150.17 | T29: Per block per month | V29: =V28/2 -> 11192.7
A31: Profit After Money Partners Funding | B31: =+C31/C26 -> 0.092532528 | C31: =C27-C28 -> 289475.8
A32: Profit After JV partners | B32: =C32/C26 -> 0.056661118 | C32: =B95 -> 177256.83
A33: Funding
A34: Private | B34: 800000 | C34: =+((B34*12%)/12)*5 -> 40000
A35: Mortgage | B35: 10000 | C35: 50000
C36: =SUM(C34:C35) -> 90000
A39: Cash required | C39: Amt
A40: Equity | B40: 0.3 | C40: =+C12*B40 -> 828000
A41: Stamp Duty | C41: =C13 -> 165600
A42: Demo | C42: =C23 -> 43000
A43: Funding Costs | C43: =C16 -> 22252
A44: Utilities | C44: =C19 -> 25000
A45: Settleing Costs | C45: =C15 -> 13000
A46: Finders Fee | C46: 40000
A47: Funders Fee | C47: =C16 -> 22252
A48: Total Cash Required | C48: =SUM(C40:C47) -> 1159104
B50: JV money | C50: Money Partners | D50: Share/ Rate | E50: Return JV | F50: MP
A51: Sharath | B51: =H4 -> 200000 | D51: =+((B51/850000)*0.45)*100% -> 0.10588235 | E51: =B51*$C$92 -> 36423.794
A52: Vivek | B52: 600000 | D52: 0.295 | E52: =B52*$C$92 -> 109271.38 | F52: =+(C52*D55/12)*5 -> 0
A53: Vijay | B53: 200000 | D53: =+((B53/850000)*0.45)*100% -> 0.10588235 | E53: =B53*$C$92 -> 36423.794
D54: =+((B54/850000)*0.45)*100% -> 0
A57: Ramakanth 6 | C57: =+H13 -> 150000 | D57: 0.15 | F57: =(C57*D57/12)*5 -> 9375
A59: Total | B59: =SUM(B51:B57) -> 1000000 | C59: =SUM(C51:C57) -> 150000 | D59: =SUM(D51:D54) -> 0.50676471 | E59: =SUM(E51:E58) -> 182118.97 | F59: =SUM(F52:F58) -> 9375
A60: Senior Debt | B60: =+H19 -> 1932000
A61: Total | B61: =+B59+B60+C59 -> 3082000
A62: Difference | B62: =B61-(E27+C48) -> -9104
A67: Stage 1
A68: Sale of Block 44 | B68: =C6 -> 1770000
A69: Minus Comissions | B69: =-B68*1.54% -> -27258 | C69: c
A70: Margin Scheme | C70: t
A71: Closing Costs | B71: -5000 | C71: c
A72: Pay back Money partners | B72: =-C59 -> -150000
A73: Balance to pay loan | B73: =SUM(B68:B72) -> 1587742
A74: Balance on loan | B74: =E27-B73 -> 344258
A78: JV Money | B78: =B59 -> 1000000
A79: Total Liabilities | B79: =SUM(B77:B78)+B74 -> 1344258
A81: Stage 2 | B81: JV
A82: Sell block 2 | B82: 1775000
A83: Selling cost | B83: =-B82*1.54% -> -27335
A84: Minus Marin Scheme
A85: Closing Costs | B85: -5000
A86: Loan Payable | B86: =-B74 -> -344258
A87: Money Partners Interest+ senior lender interest | B87: =-F59-L19 -> -39031.2
A88: Residue | B88: =SUM(B82:B87) -> 1359375.8
A90: Minus JV contribution | B90: =B88-B78 -> 359375.8
A92: JV share of the profit | B92: =B90*D59 -> 182118.97 | C92: =B92/B59 -> 0.18211897
A95: Developer share of profit | B95: =B90-B92 -> 177256.83

Sheet Budget vs actual
A1: Feasibility- submited to Vijay | D1: 46111
A2: Size of each unit | B2: Sqs | C2: Budget | D2: Actual | E2: Variance
A3: Total Build area in Sqm | B3: Sqm | C3: =+C2*9.29*C5 -> #VALUE!
A4: Land area in sqm | C4: 1295
A5: No of Dwellings | C5: 2
A6: Block 1 | C6: 1765000 | D6: 1765000
A7: Block 2 | C7: 1775000 | D7: 1725000
A8: Total Sales | C8: =+C7+C6 -> 3540000 | D8: =+D7+D6 -> 3490000
A9: GST on margin scheme
A10: Total Revenue | B10: =C10/C10 -> 1 | C10: =+C8+C9 -> 3540000 | D10: =+D8 -> 3490000 | E10: =+D10-C10 -> -50000
A11: All costs are GST exclusive | E11: =+D11-C11 -> 0
A12: Purchase price | B12: =+C12/C10 -> 0.77966102 | C12: 2760000 | D12: =C12 -> 2760000 | E12: =+D12-C12 -> 0
A13: Stamp duty + buy in Fees | B13: 0.06 | C13: =(C12+C11)*B13 -> 165600 | D13: =159400+3897.63 -> 163297.63 | E13: =+D13-C13 -> -2302.37
A14: Finders Fee | C14: 40000 | D14: 40000 | E14: =+D14-C14 -> 0
A15: Accounting & Legals | C15: 15000 | D15: =1850+5329.36 -> 7179.36 | E15: =+D15-C15 -> -7820.64
A16: Funding cost establishment cost | C16: ='Senior Funding Model'!D20 -> 22252 | D16: =7728+11726 -> 19454 | E16: =+D16-C16 -> -2798
A17: Acquisition cost | B17: =C17/C10 -> 0.84826328 | C17: =SUM(C11:C16) -> 3002852 | D17: =SUM(D12:D16) -> 2989931 | E17: =+D17-C17 -> -12921.01
A18: Due Dilligence | B18: 0.33 | C18: 0 | D18: 7088 | E18: =+D18-C18 -> 7088
A19: Utilities | B19: 0.01 | C19: 30000 | D19: =729.8+1259.5 -> 1989.3 | E19: =+D19-C19 -> -28010.7
A20: Arbourist | B20: 0.008 | C20: 0 | D20: 1540 | E20: =+D20-C20 -> 1540
A21: Marketing & selling cost | B21: 0.0154 | C21: 67260 | D21: 873 | E21: =+D21-C21 -> -66387
A22: Holding Cost | C22: 10000 | D22: =5904.14+43.65+145.01+935+841.46+5180 -> 13049.26 | E22: =+D22-C22 -> 3049.26
A23: Accounting | D23: =4400+124.68 -> 4524.68 | E23: =+D23-C23 -> 4524.68
A24: Council | D24: 276.71 | E24: =+D24-C24 -> 276.71
A25: Bank Fees | D25: 35 | E25: =+D25-C25 -> 35
A26: Demo | C26: 80000 | D26: 40000 | E26: =+D26-C26 -> -40000
A27: Misc cost | C27: 10000 | E27: =+D27-C27 -> -10000
A28: Total Development Cost | B28: =C28/C10 -> 0.055723164 | C28: =SUM(C18:C27) -> 197260 | D28: =SUM(D18:D27) -> 69375.95 | E28: =+D28-C28 -> -127884.05
A29: Total Project Cost before funding | C29: =C17+C28 -> 3200112 | D29: =D17+D28 -> 3059306.9 | E29: =+D29-C29 -> -140805.06
A30: Profit Before Funding cost | B30: =+C30/C29 -> 0.10621128 | C30: =+C10-C29 -> 339888 | D30: =+D10-D29 -> 430693.06 | E30: =+D30-C30 -> 90805.06
A31: Interest | B31: =+C31/C8 -> 0.012711864 | C31: 45000 | D31: 55000 | E31: =+D31-C31 -> 10000
A34: Profit after funding | C34: =C30-C31 -> 294888 | D34: =+D30-D31 -> 375693.06 | E34: =+D34-C34 -> 80805.06
C35: =+C34/C29 -> 0.092149275 | D35: =+D34/D29 -> 0.12280332 | E35: =E34/D29 -> 0.026412865

Sheet 1 land + 1 build
A1: Feasibility
A2: Size of each unit | B2: Sqs | C2: 42
A3: Total Build area in Sqm | B3: Sqm | C3: =C2*9.29 -> 390.18
A4: Land area in sqm | C4: 1295 | D4: =C12/C4 -> 2131.2741
A5: No of Dwellings | C5: 1 | D5: Sell per Sq M
A6: Land Sale | C6: 1765000 | D6: =C8/C4 -> 4065.6371
A7: House Sale | C7: 3500000
A8: Total Sales | C8: =C7+C6 -> 5265000
A9: GST on margin scheme | C9: =-(C7-(C12/2))*10% -> -212000
A10: Total Revenue | B10: =C10/C10 -> 1 | C10: =+C8+C9 -> 5053000
A11: All costs are GST exclusive
A12: Purchase price | B12: =+C12/C10 -> 0.54621017 | C12: 2760000
A13: Stamp duty + buy in Fees | B13: 0.06 | C13: =C12*B13 -> 165600
A14: Buyers fee | C14: 40000
A15: Accounting & Legals & Closing | C15: 15000
A16: Funding cost | C16: 30000
A17: Acquisition cost | B17: =C17/C10 -> 0.59580447 | C17: =SUM(C12:C16) -> 3010600 | D17: Build per sqm | E17: incd gst | F17: per dwelling
A18: Construction cost | B18: 0.25 | C18: =+B18*C10 -> 1263250 | D18: =C18/C3 -> 3237.6083 | E18: =D18*1.1 -> 3561.3691 | F18: =C18/C5 -> 1263250
A19: Townplannig | B19: 0.006 | C19: =$C$10*B19 -> 30318
A20: Buidling Permit Approvals | B20: 0.006 | C20: =$C$10*B20 -> 30318
A21: Holding Cost | B21: 0.005 | C21: =$C$10*B21 -> 25265
A22: Demo | C22: 80000
A23: Misc cost/contingency | B23: 0.01 | C23: =$C$10*B23 -> 50530
A24: Utilities | C24: 25000
A25: Total Development Cost | B25: =C25/C10 -> 0.29777973 | C25: =SUM(C18:C24) -> 1504681
A26: Total Project Cost before funding | C26: =C17+C25 -> 4515281
A27: Marketing & selling cost | B27: 0.0175 | C27: =B27*C8 -> 92137.5
A28: Profit Before Funding cost | B28: =+C28/C26 -> 0.098683006 | C28: =+C10-C26-C27 -> 445581.5
A29: Debt servicing expense | B29: 0 | C29: =$C$10*B29 -> 0
A33: Residual Value after selling 1 lot | B33: ='2 x Land Sales@ 70LVR'!B82 -> 1775000
A34: Senior loan payable | B34: =-'2 x Land Sales@ 70LVR'!B86+('1 land + 1 build'!C19+'1 land + 1 build'!C20+'1 land + 1 build'!C24) -> 429894
A35: Equity in land | B35: =B33-B34 -> 1345106
A36: Equity % | B36: =B35/B33 -> 0.7578062
A37: 80% LVR of land | B37: =B33*80% -> 1420000
A38: Interest | B38: =B37*6.5%*60%*1.5 -> 83070

Sheet 2 x single build
A1: Feasibility
A2: Size of each unit | B2: Sqs | C2: 42
A3: Total Build area in Sqm | B3: Sqm | C3: =+C2*9.29*C5 -> 780.36
A4: Land area in sqm | C4: 1295 | D4: =C12/C4 -> 2131.2741
A5: No of Dwellings | C5: 2 | D5: Sell per Sq M
A6: Avg Dwellings sell price | C6: 3500000 | D6: =C8/C4 -> 5405.4054
A8: Total Sales | C8: =C6*C5+C7 -> 7000000
A9: GST on margin scheme | C9: =-(C8-C12)*10% -> -424000
A10: Total Revenue | B10: =C10/C10 -> 1 | C10: =+C8+C9 -> 6576000
A11: All costs are GST exclusive | D11: Cost per Sqm
A12: Purchase price | B12: =+C12/C10 -> 0.41970803 | C12: 2760000 | D12: =+C12/C4 -> 2131.2741
A13: Stamp duty | B13: 0.06 | C13: =C12*B13 -> 165600
A14: Finders Fee | C14: 40000
A15: Accounting & Legals | C15: 15000
A16: initial Funding cost | C16: 25000
A17: Acquisition cost | B17: =C17/C10 -> 0.45705596 | C17: =SUM(C12:C16) -> 3005600 | D17: Build per sqm | E17: incd gst | F17: per dwelling
A18: Construction cost with pools | B18: 0.37 | C18: =+B18*C10 -> 2433120 | D18: =C18/C3 -> 3117.9456 | E18: =D18*1.1 -> 3429.7401 | F18: =C18/C5 -> 1216560
A19: Town planning approval | B19: 0.006 | C19: =$C$10*B19 -> 39456
A20: Buidling Permit Approvals | B20: 0.007 | C20: =$C$10*B20 -> 46032
A21: Holding Cost | B21: 0.01 | C21: 50000
A22: Demo | C22: 80000
A23: Misc cost | B23: 0.007 | C23: =$C$10*B23 -> 46032
A24: Utilities | C24: 25000
A25: Total Development Cost | B25: =C25/C10 -> 0.41357056 | C25: =SUM(C18:C24) -> 2719640
A26: Total Project Cost before funding | C26: =C17+C25 -> 5725240
A27: Marketing & selling cost | B27: 0.0185 | C27: =$C$10*B27 -> 121656
A28: Profit Before Funding cost | B28: =+C28/C26 -> 0.12734907 | C28: =+C10-C26-C27 -> 729104
A29: Debt servicing expense | C29: =C39 -> 342496
A34: Loan interest for land until contruction refinance | C34: 40000
A35: Refinance available 80% Of Net GRV | C35: =C10*80% -> 5260800
A36: Lending Fees | B36: 0.02 | C36: =B36*C35 -> 105216
A37: Interest | B37: 0.075 | C37: =C35*B37*50% -> 197280
A39: Total debt financeing cost | C39: =C34+C36+C37 -> 342496

Sheet Sell 1 hold 1 at 70% LVR
A1: Feasibility
A2: Size of each unit | B2: Sqs | C2: 0 | F2: Money Partners | AA2: Settlement
A3: Total Build area in Sqm | B3: Sqm | C3: =+C2*9.29*C5 -> 0 | G3: Loan# | H3: Amt | I3: Month Loaned | J3: No. of Month | K3: Interest rate | L3: Interest | M3: Total Amt | AA3: May
A4: Land area in sqm | C4: 1295 | F4: Sharath | G4: 1 | H4: 70000 | I4: 45717 | J4: 15 | K4: 0.15 | L4: =(J4/12)*(H4*K4) -> 13125
A5: No of Dwellings | C5: 1 | E5: Sell per Sq M | G5: 2 | H5: =200000-H4 -> 130000 | I5: 45992 | J5: 5 | K5: 0.15 | L5: =(J5/12)*(H5*K5) -> 8125 | M5: =SUM(L4:L5) -> 21250
A6: Avg Dwellings sell price | B6: 2430 | C6: =1760000 -> 1760000 | E6: =C8/C4 -> 1359.0734 | G6: Total | H6: =SUM(H4:H5) -> 200000
A8: Total Sales | C8: =C6*C5+C7 -> 1760000 | F8: Vivek | G8: 1 | H8: 70000 | I8: 45748 | J8: 15 | K8: 0.15 | L8: =(J8/12)*(H8*K8) -> 13125
A9: GST on margin scheme | G9: 2 | H9: 100000 | I9: 46023 | J9: 5 | K9: 0.15 | L9: =(J9/12)*(H9*K9) -> 6250
A10: Total Revenue | B10: =C10/C10 -> 1 | C10: =+C8+C9 -> 1760000 | G10: 3 | H10: =400000-H9-H8 -> 230000 | I10: 46023 | J10: 5 | K10: 0.15 | L10: =(J10/12)*(H10*K10) -> 14375 | M10: =SUM(L8:L10) -> 33750
A11: All costs are GST exclusive | E11: Cost per Sqm | G11: Total | H11: =SUM(H8:H10) -> 400000
A12: Purchase price | C12: 2760000 | E12: =+C12/C4 -> 2131.2741 | F12: Total Capital | H12: =+H6+H11 -> 600000
A13: Stamp duty + buy in Fees | B13: 0.06 | C13: =(C12+C11)*B13 -> 165600
A14: Finders Fee | C14: 40000 | F14: Ramakanth | G14: 1 | H14: 150000 | I14: 46023 | J14: 5 | K14: 0.15 | L14: =(J14/12)*(H14*K14) -> 9375 | M14: =+L14 -> 9375
A15: Accounting & Legals | C15: 15000 | F15: Investor 4 | G15: 1 | H15: 250000 | I15: 46023 | J15: 5 | K15: 0.15 | L15: =(J15/12)*(H15*K15) -> 15625 | M15: =+L15 -> 15625
A16: Funding Fee | C16: ='Senior Funding Model'!D20 -> 22252
A17: Acquisition cost | B17: =C17/C10 -> 1.7061659 | C17: =SUM(C11:C16) -> 3002852
A18: Water Tappings | F18: Capital amt | H18: =+H12+H14+H15 -> 1000000 | K18: Total Interest | L18: =SUM(L4:L17) -> 80000
A19: Utilities | B19: 0.01 | C19: 25000
B20: 0.008 | F20: Senior Debt | G20: 1 | H20: =#REF! -> #REF! | I20: 46023 | J20: 5 | K20: 0.08 | L20: =(J20/12)*(H20*K20) -> #REF!
A21: Marketing & selling cost | B21: 0.0165 | C21: =$C$10*B21 -> 29040
A22: Holding Cost | C22: 5000 | F22: Total | H22: =H20+H18 -> #REF! | J22: Total Funding Cost | L22: =+L20+L18 -> #REF!
A23: Demo | C23: 70000 | F23: Net Cashflow
A24: Misc cost
A25: Funding cost establishment cost
A26: Total Development Cost | B26: =C26/C10 -> 0.073318182 | C26: =SUM(C18:C25) -> 129040 | E26: Loan | F26: Cash required | R26: Burn Rate | T26: Amt | U26: Rate | V26: Per month
E27: =C12*70% -> 1932000 | F27: =C17+C19+C22+C23-E27 -> 1170852 | R27: Senior Debt | T27: =H20 -> #REF! | U27: =K20 -> 0.08 | V27: =T27*U27/12 -> #REF!
A31: Minus Net sales from 1 block | C31: =C10 -> 1760000
A32: Minus sales commission | C32: =-C21 -> -29040
A33: pay off loan amount | C33: -1709468
C35: =SUM(C30:C34) -> 21492
A37: Initial loan amount | C37: =+E27 -> 1932000
A38: Minus Principle paid off | C38: =-C33 -> 1709468
A39: Balance of loan | C39: =+C37-C38 -> 222532
A41: Initial cash required | C41: =+F27 -> 1170852
A42: JV partners contribution | C42: ='Capital Stack'!B25 -> 1145000
A43: Money partners contribution | C43: =+C41-C42 -> 25852
C45: Y 1 | D45: Yr 2 | E45: Yr 3
A46: If sell the secon block | C46: 1850000 | D46: 1900000 | E46: 2000000
A47: Loan | C47: =$C$39 -> 222532 | D47: =$C$39 -> 222532 | E47: =$C$39 -> 222532
A48: JV Partners | C48: =$C42 -> 1145000 | D48: =$C42 -> 1145000 | E48: =$C42 -> 1145000
A49: Money partners | C49: =+$C43 -> 25852 | D49: =+$C43 -> 25852 | E49: =+$C43 -> 25852
A50: Closing cost & commision | C50: =+(C46*1.5%)+5000 -> 32750 | D50: =+(D46*1.5%)+5000 -> 33500 | E50: =+(E46*1.5%)+5000 -> 35000
A51: Margin scheme | C51: =(C46-(C12/2))*10% -> 47000 | D51: =(D46-($C12/2))*10% -> 52000 | E51: =(E46-($C12/2))*10% -> 62000
A52: Interest on Senior lending | B52: 0.06 | D52: =+D47*6% -> 13351.92 | E52: =+E47*6% -> 13351.92
A53: Interest on money partners | B53: 0.15 | D53: =$B53*D49 -> 3877.8 | E53: =$B53*E49 -> 3877.8
A54: Holding Cost | D54: 5000 | E54: 5000
A55: Land Tax | D55: 5000 | E55: 5000
A56: Total cost | C56: =SUM(C47:C55) -> 1473134 | D56: =SUM(D47:D55) -> 1506113.7 | E56: =SUM(E47:E55) -> 1517613.7
A57: Balance profit project with Money Partners | C57: =C46-C56 -> 376866 | D57: =D46-D56 -> 393886.28 | E57: =E46-E56 -> 482386.28
A59: Balance with full JV @ 60% | C59: =+C57+C53 -> 376866 | D59: =+D57+D53 -> 397764.08 | E59: =+E57+E53 -> 486264.08
A60: Developer share | B60: 0.4 | C60: =+C59*$B60 -> 150746.4 | D60: =+D59*$B60 -> 159105.63 | E60: =+E59*$B60 -> 194505.63

Sheet 7 Yr Valuation & Cashflow JV
A1: Yr # | C1: 1 | D1: 2 | E1: 3 | F1: 4 | G1: 5 | H1: 6 | I1: 7
A2: Financial Yr | C2: 2026 | D2: 2027 | E2: 2028 | F2: 2029 | G2: 2030 | H2: 2031 | I2: 2032
A3: Capital Growth | D3: =(D5-C5)/C5 -> 0.23188406 | E3: 0.05 | F3: 0.05 | G3: 0.05 | H3: 0.05 | I3: 0.05
A4: Valuation per block | C4: =+C5/2 -> 1380000 | D4: =+D5/2 -> 1700000 | E4: =+E5/2 -> 1785000 | F4: =+F5/2 -> 1874250 | G4: =+G5/2 -> 1967962.5 | H4: =+H5/2 -> 2066360.6 | I4: =+I5/2 -> 2169678.7
A5: Property Valuation | C5: 2760000 | D5: =1700000*2 -> 3400000 | E5: =+D5*(100%+E3) -> 3570000 | F5: =+E5*(100%+F3) -> 3748500 | G5: =+F5*(100%+G3) -> 3935925 | H5: =+G5*(100%+H3) -> 4132721.2 | I5: =+H5*(100%+I3) -> 4339357.3
A6: Increase In Value | D6: =+D5-C5 -> 640000 | E6: =+E5-D5 -> 170000 | F6: =+F5-E5 -> 178500 | G6: =+G5-F5 -> 187425 | H6: =+H5-G5 -> 196796.25 | I6: =+I5-H5 -> 206636.06 | K6: 800000
A7: StampDuty | C7: =C5*6% -> 165600 | J7: The is a land with 2 titles
A8: Closing cost + Due Diligence | C8: 8000 | J8: Can I nominate it as main residence to get CGT excemption - intention is to renovate a unit and move in - But we may consider to re-develop the land or sell it within 7 years.
A9: Finders fee | C9: 30000 | J9: Can I borrow money from a friends SMSF as a personal loan towards Equity for the purchase. If that’s not possible, Homelsy Pty can borrow but how to I get that across towards Equity towards Purchase
A10: Operating Reserve & Repairs | C10: 60000
A11: Total Cost | C11: =SUM(C5:C10) -> 3023600
A13: Loan @ 70% LVR | C13: =C5*70% -> 1932000 | D13: =D5*70% -> 2380000 | E13: =E5*70% -> 2499000 | F13: =F5*70% -> 2623950 | G13: =G5*70% -> 2755147.5 | H13: =H5*70% -> 2892904.9 | I13: =I5*70% -> 3037550.1
A14: Equity required @ 30% purchase | C14: =+C5*30% -> 828000 | D14: =+D5*30% -> 1020000 | E14: =+E5*30% -> 1071000 | F14: =+F5*30% -> 1124550 | G14: =+G5*30% -> 1180777.5 | H14: =+H5*30% -> 1239816.4 | I14: =+I5*30% -> 1301807.2
A15: Private Funds Required incd costs | C15: =C11-C13 -> 1091600
A16: JV at 80% Equity | B16: =+C16/C15 -> 0.91608648 | C16: 1000000 | D16: 1000000 | E16: 1000000 | F16: 1000000 | G16: 1000000 | H16: 800000 | I16: 800000
A17: Dev Equity | B17: =C17/C15 -> 0.083913521 | C17: =C15-C16 -> 91600 | D17: =C17 -> 91600 | E17: =D17 -> 91600 | F17: =E17 -> 91600 | G17: =F17 -> 91600 | H17: =G17 -> 91600 | I17: =H17 -> 91600
A18: Dev Private Iinterest | B18: 0.12 | C18: =(C17*12%)/2 -> 5496 | D18: =(D17*12%) -> 10992 | E18: =(E17*12%) -> 10992 | F18: =(F17*12%) -> 10992 | G18: =(G17*12%) -> 10992 | H18: =(H17*12%) -> 10992 | I18: =(I17*12%) -> 10992
A20: If sold Profit | C20: =D5-C5-C7-C8-C9-C10-C18 -> 370904 | D20: =E5-C11+C48-D18-C18 -> 512722.4 | E20: =F5-C11+C48+D48-C18-D18-E18 -> 676394.4 | F20: =G5-C11+C48+D48+E48-C18-D18-E18-F18 -> 858919 | G20: =H5-C11+C48+D48+E48+F48+G48-C18-D18-E18-F18-G18 -> 1128503.5
A21: Profit Increase | D21: =D20/C20-100% -> 0.38235878 | E21: =E20/D20-100% -> 0.31922147 | F21: =F20/E20-100% -> 0.26984937 | G21: =G20/F20-100% -> 0.31386481
A22: JV Proft Split | B22: 0.7 | C22: =C20*$B$22 -> 259632.8 | D22: =D20*$B$22 -> 358905.68 | E22: =E20*$B$22 -> 473476.08 | F22: =F20*$B$22 -> 601243.3 | G22: =G20*$B$22 -> 789952.42
A23: dev Return % | C23: =+C22/C16*2 -> 0.5192656 | D23: =(D22/D16)/1.5 -> 0.23927045 | E23: =(E22/E16)/2.5 -> 0.18939043 | F23: =(F22/F16)/3.5 -> 0.1717838 | G23: =(G22/G16)/4.5 -> 0.17554498
A25: Dev Profit Split | B25: =100%-B22 -> 0.3 | C25: =$B$25*C20 -> 111271.2 | D25: =$B$25*D20 -> 153816.72 | E25: =$B$25*E20 -> 202918.32 | F25: =$B$25*F20 -> 257675.7 | G25: =$B$25*G20 -> 338551.04
A26: Dev Profit -minus Private Interest | C26: =C25-C18 -> 105775.2 | D26: =D25-D18-C18 -> 137328.72 | E26: =E25-E18-D18-C18 -> 175438.32 | F26: =F25-F18-E18-D18-C18 -> 219203.7 | G26: =G25-G18-F18-E18-D18-C18 -> 289087.04
A29: Cashflow
A30: Rental Growth | D30: 0.05 | E30: =+E31/D31 -> 1.0683007 | F30: 0.04 | G30: 0.04 | H30: 0.04 | I30: 0.04
A31: Rev | C31: ='Cash Flow FY1'!B22 -> 69120 | D31: ='Cash Flow FY2'!B21 -> 183600 | E31: ='Cash Flow FY3'!B21 -> 196140 | F31: ='Cash Flow FY4'!B21 -> 206550 | G31: ='Cash Flow FY5'!B21 -> 216750 | H31: ='Cash Flow FY4'!D21 -> 16200 | I31: ='Cash Flow FY4'!E21 -> 20250
A32: Expenes
A33: Interest Payments | C33: ='Cash Flow FY1'!B3 -> 59312.4 | D33: ='Cash Flow FY2'!B2 -> 115920 | E33: ='Cash Flow FY3'!B2 -> 115920 | F33: ='Cash Flow FY4'!B2 -> 115920 | G33: =+F33*(100%+$B$33) -> 115920 | H33: =+G33*(100%+$B$33) -> 115920 | I33: =+H33*(100%+$B$33) -> 115920
A34: Council Rates | C34: ='Cash Flow FY1'!B4 -> 6350 | D34: ='Cash Flow FY2'!B3 -> 12720 | E34: ='Cash Flow FY3'!B3 -> 12780 | F34: ='Cash Flow FY4'!B3 -> 13163.4 | G34: =+F34*(100%+$B34) -> 13163.4 | H34: =+G34*(100%+$B34) -> 13163.4 | I34: =+H34*(100%+$B34) -> 13163.4
A35: Insurance | C35: ='Cash Flow FY1'!B5 -> 3000 | D35: ='Cash Flow FY2'!B4 -> 6000 | E35: ='Cash Flow FY3'!B4 -> 7800 | F35: ='Cash Flow FY4'!B4 -> 8400 | G35: =+F35*(100%+$B35) -> 8400 | H35: =+G35*(100%+$B35) -> 8400 | I35: =+H35*(100%+$B35) -> 8400
A36: Landscaping | C36: ='Cash Flow FY1'!B6 -> 1500 | D36: ='Cash Flow FY2'!B5 -> 3600 | E36: ='Cash Flow FY3'!B5 -> 3600 | F36: ='Cash Flow FY4'!B5 -> 3600 | G36: =+F36*(100%+$B36) -> 3600 | H36: =+G36*(100%+$B36) -> 3600 | I36: =+H36*(100%+$B36) -> 3600
A37: Repairs & Maintaince | C37: ='Cash Flow FY1'!B7 -> 2500 | D37: ='Cash Flow FY2'!B6 -> 6180 | E37: ='Cash Flow FY3'!B6 -> 6180 | F37: ='Cash Flow FY4'!B6 -> 6180 | G37: =+F37*(100%+$B37) -> 6180 | H37: =+G37*(100%+$B37) -> 6180 | I37: =+H37*(100%+$B37) -> 6180
A38: Property Management | C38: ='Cash Flow FY1'!B8 -> 4147.2 | D38: ='Cash Flow FY2'!B7 -> 11016 | E38: ='Cash Flow FY3'!B7 -> 11768.4 | F38: ='Cash Flow FY4'!B7 -> 12393
A39: Misc | C39: ='Cash Flow FY1'!B9 -> 5500 | D39: ='Cash Flow FY2'!B8 -> 2000 | E39: ='Cash Flow FY3'!B8 -> 2000 | F39: ='Cash Flow FY4'!B8 -> 2000 | G39: ='Cash Flow FY4'!C8 -> 0 | H39: ='Cash Flow FY4'!D8 -> 0 | I39: ='Cash Flow FY4'!E8 -> 1000
A40: Land Tax | C40: ='Cash Flow FY1'!B10 -> 0 | D40: 30000 | E40: 30000 | F40: 30000
A41: Letting Fee | C41: ='Cash Flow FY1'!B11 -> 2000 | D41: ='Cash Flow FY2'!B10 -> 0 | E41: ='Cash Flow FY3'!B10 -> 0 | F41: ='Cash Flow FY4'!B10 -> 0 | G41: 600 | H41: 600 | I41: 600
A42: Advertising | C42: ='Cash Flow FY1'!B12 -> 2000 | D42: ='Cash Flow FY2'!B11 -> 0 | E42: ='Cash Flow FY3'!B11 -> 0 | F42: ='Cash Flow FY4'!B11 -> 0 | G42: =+F42*(100%+$B42) -> 0 | H42: =+G42*(100%+$B42) -> 0 | I42: =+H42*(100%+$B42) -> 0
A47: Total Expense | C47: =SUM(C33:C43) -> 86309.6 | D47: =SUM(D33:D43) -> 187436 | E47: =SUM(E33:E43) -> 190048.4 | F47: =SUM(F33:F43) -> 191656.4 | G47: =SUM(G33:G43) -> 147863.4 | H47: =SUM(H33:H43) -> 147863.4 | I47: =SUM(I33:I43) -> 148863.4
A48: Net Cashflow | C48: =C31-C47 -> -17189.6 | D48: =D31-D47 -> -3836 | E48: =E31-E47 -> 6091.6 | F48: =F31-F47 -> 14893.6 | G48: =G31-G47 -> 68886.6 | H48: =H31-H47 -> -131663.4 | I48: =I31-I47 -> -128613.4
A49: Net operating Profit | C49: =C48+C33 -> 42122.8 | D49: =D48+D33 -> 112084 | E49: =E48+E33 -> 122011.6 | F49: =F48+F33 -> 130813.6 | G49: =G48+G33 -> 184806.6 | H49: =H48+H33 -> -15743.4 | I49: =I48+I33 -> -12693.4
A50: Cap Rate | D50: =+D49/C5 -> 0.040610145 | E50: =+E49/D5 -> 0.035885765 | F50: =+F49/E5 -> 0.036642465 | G50: =+G49/F5 -> 0.049301481 | H50: =+H49/G5 -> -0.0039999238 | I50: =+I49/H5 -> -0.0030714387
C53: 45748 | D53: 46023
A54: Stage 1 Funding | C54: Stage 1 | D54: Stage 2
A55: Total | C55: =SUM(C56:C60) -> 135000 | D55: =SUM(D56:D64) -> 680600
A56: Due Dilligence | C56: 5000
A57: Deposit | C57: 100000
A58: Finders Fee | C58: =C9 -> 30000
A59: Equity | D59: =2760000*20%-C57 -> 452000
A60: Spamp Duty | D60: =C7 -> 165600
A61: Reno/ Repairs | D61: =C10 -> 60000
A62: Closing costs | D62: 3000

Sheet Senior Funding Model
A1: As of 28th October | B1: Think Tank 70% | C1: Think Tank 80% | D1: Westpac 70%
A2: Loan Amount | B2: =70%*2760000 -> 1932000 | C2: =80%*2760000 -> 2208000 | D2: =2760000*70% -> 1932000 | F2: Inputs | J2: Servicability Requirements
A3: Equity Required | B3: =3150000-B2 -> 1218000 | C3: =3150000-C2 -> 942000 | D3: =3150000-D2 -> 1218000 | F3: Purchase price | G3: ='7 Yr Valuation & Cashflow'!C5 -> 2760000 | K3: Loan Amt | L3: Interest | M3: Net Income Req | N3: Fixed Expense | O3: Flexible Exp | P3: Net Rent | Q3: Sinead IncomeNet | R3: Sub Total | S3: Net KR Salary | T3: KR Gross Saalry
A4: Costs | F4: Interest rate assessed | G4: 0.075 | J4: =F6 -> LVR 80% | K4: =G3*G6 -> 2208000 | L4: =K4*(G$4+G$5) -> 231840 | M4: =L4*G$9 -> 347760 | N4: -54000 | O4: 0 | P4: =H24 -> 128250 | Q4: 66228 | R4: =SUM(N4:Q4) -> 140478 | S4: =M4-R4 -> 207282 | T4: 350000
A5: Broker Fee | B5: 0 | C5: 0 | D5: 0.0055 | F5: Buffer | G5: 0.03 | J5: =F7 -> LVR 70% | K5: =G3*G7 -> 1932000 | L5: =K5*(G$4+G$5) -> 202860 | M5: =L5*G$9 -> 304290 | N5: -54000 | O5: 0 | P5: =G$24 -> 120042 | Q5: 66228 | R5: =SUM(N5:Q5) -> 132270 | S5: =M5-R5 -> 172020 | T5: 265000
A6: Establishment Fee | B6: 0.00475 | C6: 0.00475 | D6: 0.006 | F6: LVR 80% | G6: 0.8 | J6: =F8 -> LVR 65% | K6: =G3*G8 -> 1794000 | L6: =K6*(G$4+G$5) -> 188370 | M6: =L6*G$9 -> 282555 | N6: -54000 | O6: 0 | P6: =G$24 -> 120042 | Q6: 66228 | R6: =SUM(N6:Q6) -> 132270 | S6: =M6-R6 -> 150285 | T6: 225000
A7: Legals | B7: 0.001 | C7: 0.001 | D7: 0 | F7: LVR 70% | G7: 0.7
A8: Settlement Fee | B8: 495 | C8: 495 | D8: 1000 | F8: LVR 65% | G8: 0.65
A9: Deffered Fee (months Interest) | B9: 0.083333333 | C9: 0.083333333 | D9: 0 | F9: Servicability Ratio to Income | G9: 1.5
A10: Interest Rate | B10: 0.0769 | C10: 0.0817 | D10: 0.0614 | F10: Income Considered from Rent | G10: 0.9
A11: Interest per year | B11: =+B10*B2 -> 148570.8 | C11: =+C10*C2 -> 180393.6 | D11: =+D10*D2 -> 118624.8 | F11: Vacancy Rate | G11: 0.05
A12: Fee | F12: Monthly Household Expenses w/ 1 dependant | G12: 4500
A13: Broker Fee | B13: =+B5*B2 -> 0 | C13: =+C5*C2 -> 0 | D13: =0.005*D2 -> 9660
A14: Establishment Fee | B14: =+B6*B2 -> 9177 | C14: =+C6*C2 -> 10488 | D14: =+D6*D2 -> 11592
A15: Legals | B15: =+B7*B2 -> 1932 | C15: =+C7*C2 -> 2208 | D15: =+D7*D2 -> 0 | F15: Annual Expenses
A16: Settlement Fee | B16: =B8 -> 495 | C16: =C8 -> 495 | D16: =D8 -> 1000 | F16: Monthly Expenses | G16: =+G12*12 -> 54000
A17: Deffered Fee (months Interest) | B17: =B2*B10*B9 -> 12380.9 | C17: =C2*C10*C9 -> 15032.8 | D17: =D2*D10*D9 -> 0 | F17: Flexible Expense
F18: 657A Nepean Hwy Loan | G18: =6900*12 -> 82800
F19: Total Expenses | G19: =SUM(G16:G18) -> 136800
A20: Total Fees | B20: =SUM(B13:B19) -> 23984.9 | C20: =SUM(C13:C19) -> 28223.8 | D20: =SUM(D13:D19) -> 22252
F21: Rent | G21: 270 | H21: 290
F22: Rental Income | G22: 140400 | H22: 150000
F23: Net rental income (after 5% vacancy) | G23: =G22*(100%-G11) -> 133380 | H23: =+H22*(100%-G11) -> 142500
F24: Rental shading 90% | G24: =G23*G10 -> 120042 | H24: =H23*G10 -> 128250

Sheet 7 Yr Valuation & Cashflow
A1: Yr # | C1: 1 | D1: 2 | E1: 3 | F1: 4 | G1: 5 | H1: 6 | I1: 7
A2: Financial Yr | C2: 2026 | D2: 2027 | E2: 2028 | F2: 2029 | G2: 2030 | H2: 2031 | I2: 2032
A3: Capital Growth | D3: =(D5-C5)/C5 -> 0.37681159 | E3: 0.05 | F3: 0.05 | G3: 0.05 | H3: 0.05 | I3: 0.05
A4: Valuation per block | C4: =+C5/2 -> 1380000 | D4: =+D5/2 -> 1900000 | E4: =+E5/2 -> 1995000 | F4: =+F5/2 -> 2094750 | G4: =+G5/2 -> 2199487.5 | H4: =+H5/2 -> 2309461.9 | I4: =+I5/2 -> 2424935 | K4: Cash required | L4: Capital stack
A5: Property Valuation | C5: 2760000 | D5: =1900000*2 -> 3800000 | E5: =+D5*(100%+E3) -> 3990000 | F5: =+E5*(100%+F3) -> 4189500 | G5: =+F5*(100%+G3) -> 4398975 | H5: =+G5*(100%+H3) -> 4618923.8 | I5: =+H5*(100%+I3) -> 4849869.9 | K5: Equity | L5: =C5*30% -> 828000
A6: Increase In Value | D6: =+D5-C5 -> 1040000 | E6: =+E5-D5 -> 190000 | F6: =+F5-E5 -> 199500 | G6: =+G5-F5 -> 209475 | H6: =+H5-G5 -> 219948.75 | I6: =+I5-H5 -> 230946.19 | K6: Working Capital | L6: ='Capital Stack'!B9-'7 Yr Valuation & Cashflow'!L5-'Capital Stack'!B13 -> 371892
A7: StampDuty | C7: =C5*6% -> 165600
A8: Closing cost + Due Diligence | C8: 15000 | K8: Total Cash Required | L8: =SUM(L5:L7) -> 1199892
A9: Finders fee | C9: 40000 | K9: Loan | L9: =+'Capital Stack'!B13 -> 1932000
A10: Operating Reserve & Repairs | C10: =150000+30000 -> 180000 | K10: Capital Stack | L10: =SUM(L8:L9) -> 3131892
A11: Finance Cost | C11: ='Senior Funding Model'!D20 -> 22252
A12: Total Cost | C12: =SUM(C5:C11) -> 3182852 | L12: Amt | M12: Share
K13: Capital Raised - Round 1 | L13: 800000 | M13: =+(L13/850000)*0.45 -> 0.42352941
A14: Loan @ 70% LVR | C14: =C5*70% -> 1932000 | D14: =C14 -> 1932000 | E14: =E5*70% -> 2793000 | F14: =F5*70% -> 2932650 | G14: =G5*70% -> 3079282.5 | H14: =H5*70% -> 3233246.6 | I14: =I5*70% -> 3394909 | K14: Deficit - Round 2 | L14: =+L8-L13 -> 399892 | M14: 0.18
A15: Equity / cash Required | C15: =L8 -> 1199892 | D15: =C15 -> 1199892 | E15: =D15 -> 1199892 | F15: =E15 -> 1199892 | G15: =F15 -> 1199892 | H15: =+H5*30% -> 1385677.1 | I15: =+I5*30% -> 1454961 | K15: Total Investors | L15: =SUM(L13:L14) -> 1199892 | M15: =SUM(M13:M14) -> 0.60352941
A16: Refinance Surplus | C16: 0 | D16: =+D14-C14 -> 0 | E16: =+E14-D14 -> 861000 | F16: =+F14-E14 -> 139650 | G16: =+G14-F14 -> 146632.5 | H16: =+H14-G14 -> 153964.12 | I16: =+I14-H14 -> 161662.33 | K16: Developer | L16: 0 | M16: =100%-M15 -> 0.39647059
H17: =H5*20%-#REF! -> #REF! | I17: =I5*20%-#REF! -> #REF!
A18: Exit Model | H18: =+H5-G14-#REF!-#REF!-5000 -> #REF! | I18: =+I5-H14-#REF!-#REF!-5000 -> #REF!
A19: Sales commission-1.65% | D19: =1.65%*D5+10000 -> 72700 | E19: =1.65%*E5+10000 -> 75835 | F19: =1.65%*F5+10000 -> 79126.75 | G19: =1.65%*G5+10000 -> 82583.088 | H19: =H5-$C$5 -> 1858923.8 | I19: =I5-$C$5 -> 2089869.9
A20: Closing Costs | C20: =C18*$B$20 -> 0 | D20: 5000 | E20: 5001 | F20: 5002 | G20: 5003 | H20: =H18-((H19/2)*32%) -> #REF! | I20: =I18-((I19/2)*32%) -> #REF! | L20: Think Tank
A21: Cost of selling | C21: =C18*$B$21 -> 0 | D21: =+D19+D20 -> 77700 | E21: =+E19+E20 -> 80836 | F21: =+F19+F20 -> 84128.75 | G21: =+G19+G20 -> 87586.088 | H21: 800000 | I21: 800000 | K21: Feasibility | L21: Refinancing | M21: Sale
A22: Profit $ | D22: =D5-$C$12-D21 -> 539448 | E22: =E5-$C$12-E21 -> 726312 | F22: =F5-$C$12-F21 -> 922519.25 | G22: =G5-$C$12-G21 -> 1128536.9 | H22: =G22 -> 1128536.9 | I22: =H22 -> 1128536.9 | L22: Amt | M22: Amt
A23: Profit % | D23: =D22/$C$12 -> 0.16948573 | E23: =E22/$C$12 -> 0.22819534 | F23: =F22/$C$12 -> 0.28984045 | G23: =G22/$C$12 -> 0.35456783 | K23: Sale of Property | L23: 3800000 | M23: 3800000
H24: =+H22/2 -> 564268.46 | I24: =+I22/2 -> 564268.46 | K24: Net Rental cashflow incd outgoings | L24: -5000 | M24: -5000
A25: Developer Profit | B25: =M16 -> 0.39647059 | D25: =+D22*$B25 -> 213875.27 | E25: =+E22*$B25 -> 287961.35 | F25: =+F22*$B25 -> 365751.75 | G25: =+G22*$B25 -> 447431.69 | H25: =+H22*35% -> 394987.92 | I25: =+I22*35% -> 394987.92 | K25: Total Revenue | L25: =SUM(L23:L24) -> 3795000 | M25: =SUM(M23:M24) -> 3795000
A26: Investor Profit | B26: =M15 -> 0.60352941 | D26: =D22*$B$26 -> 325572.73 | E26: =E22*$B$26 -> 438350.65 | F26: =F22*$B$26 -> 556767.5 | G26: =G22*$B$26 -> 681105.22 | K26: Purchase Price | L26: 2760000 | M26: 2760000
A27: Investors returns % per Yr | D27: =(D26/$L$15)/(D1-1) -> 0.27133503 | E27: =(E26/$L$15)/(E1-1) -> 0.18266255 | F27: =(F26/$L$15)/(F1-1) -> 0.15467156 | G27: =(G26/$L$15)/(G1-1) -> 0.14190969 | K27: StampDuty | L27: =L26*6% -> 165600 | M27: =M26*6% -> 165600
A28: Total Investor Retunr | D28: =D26/$L$15 -> 0.27133503 | E28: =E26/$L$15 -> 0.36532509 | F28: =F26/$L$15 -> 0.46401468 | G28: =G26/$L$15 -> 0.56763877 | K28: Closing cost + Due Diligence | L28: 15000 | M28: 15000
A29: Rental Growth | D29: 0.05 | E29: =(E30/D30)-100% -> 0.068300654 | F29: =(F30/E30)-100% -> 0.053074335 | G29: =(G30/F30)-100% -> 0.049382716 | H29: =(H30/G30)-100% -> -0.92525952 | I29: =(I30/H30)-100% -> 0.25 | K29: Finders fee | L29: 40000 | M29: 40000
A30: Rev | C30: ='Cash Flow FY1'!B22 -> 69120 | D30: ='Cash Flow FY2'!B21 -> 183600 | E30: ='Cash Flow FY3'!B21 -> 196140 | F30: ='Cash Flow FY4'!B21 -> 206550 | G30: ='Cash Flow FY5'!B21 -> 216750 | H30: ='Cash Flow FY4'!D21 -> 16200 | I30: ='Cash Flow FY4'!E21 -> 20250 | K30: Operating Reserve & Repairs | L30: 150000 | M30: 150000
A31: Expenes | K31: Finance Cost (settlement) | L31: 20000 | M31: 20000
A32: Interest Payments | C32: ='Cash Flow FY1'!B3 -> 59312.4 | D32: ='Cash Flow FY2'!B2 -> 115920 | E32: ='Cash Flow FY3'!B2 -> 115920 | F32: ='Cash Flow FY4'!B2 -> 115920 | G32: ='Cash Flow FY5'!B2 -> 115920 | H32: =+G32*(100%+$B$32) -> 115920 | I32: =+H32*(100%+$B$32) -> 115920 | K32: Refinancing cost | L32: 30000
A33: Outgoings | K33: Sales commission & Marketing cost | M33: =+M23*1.5% + 10000 -> 67000
A34: Council Rates | C34: ='Cash Flow FY1'!B4 -> 6350 | D34: ='Cash Flow FY2'!B3 -> 12720 | E34: ='Cash Flow FY3'!B3 -> 12780 | F34: ='Cash Flow FY4'!B3 -> 13163.4 | G34: ='Cash Flow FY5'!B3 -> 15600 | H34: =+G34*(100%+$B34) -> 15600 | I34: =+H34*(100%+$B34) -> 15600 | K34: Total Cost | L34: =SUM(L26:L33) -> 3180600 | M34: =SUM(M26:M33) -> 3217600
A35: Insurance | C35: ='Cash Flow FY1'!B5 -> 3000 | D35: ='Cash Flow FY2'!B4 -> 6000 | E35: ='Cash Flow FY3'!B4 -> 7800 | F35: ='Cash Flow FY4'!B4 -> 8400 | G35: ='Cash Flow FY5'!B4 -> 8400 | H35: =+G35*(100%+$B35) -> 8400 | I35: =+H35*(100%+$B35) -> 8400
A36: Landscaping | C36: ='Cash Flow FY1'!B6 -> 1500 | D36: ='Cash Flow FY2'!B5 -> 3600 | E36: ='Cash Flow FY3'!B5 -> 3600 | F36: ='Cash Flow FY4'!B5 -> 3600 | G36: ='Cash Flow FY5'!B5 -> 3600 | H36: =+G36*(100%+$B36) -> 3600 | I36: =+H36*(100%+$B36) -> 3600 | K36: Profit $ | L36: =L25-L34 -> 614400 | M36: =M25-M34 -> 577400
A37: Repairs & Maintaince | C37: ='Cash Flow FY1'!B7 -> 2500 | D37: ='Cash Flow FY2'!B6 -> 6180 | E37: ='Cash Flow FY3'!B6 -> 6180 | F37: ='Cash Flow FY4'!B6 -> 6180 | G37: ='Cash Flow FY5'!B6 -> 6180 | H37: =+G37*(100%+$B37) -> 6180 | I37: =+H37*(100%+$B37) -> 6180 | K37: Profit on cost | L37: =+L36/L34 -> 0.1931711 | M37: =+M36/M34 -> 0.17945052
A38: Property Management | C38: ='Cash Flow FY1'!B8 -> 4147.2 | D38: ='Cash Flow FY2'!B7 -> 11016 | E38: ='Cash Flow FY3'!B7 -> 11768.4 | F38: ='Cash Flow FY4'!B7 -> 12393 | G38: ='Cash Flow FY5'!B7 -> 13005 | H38: ='Cash Flow FY4'!D7 -> 972 | I38: ='Cash Flow FY4'!E7 -> 1215
A39: Misc | C39: ='Cash Flow FY1'!B9 -> 5500 | D39: ='Cash Flow FY2'!B8 -> 2000 | E39: ='Cash Flow FY3'!B8 -> 2000 | F39: ='Cash Flow FY4'!B8 -> 2000 | G39: ='Cash Flow FY5'!B8 -> 2000 | H39: ='Cash Flow FY4'!D8 -> 0 | I39: ='Cash Flow FY4'!E8 -> 1000
A40: Land Tax | C40: ='Cash Flow FY1'!B10 -> 0 | D40: ='Cash Flow FY2'!$B9 -> 29000 | E40: ='Cash Flow FY2'!$B9 -> 29000 | F40: ='Cash Flow FY2'!$B9 -> 29000 | G40: ='Cash Flow FY2'!$B9 -> 29000
A41: Letting Fee | C41: ='Cash Flow FY1'!B11 -> 2000 | D41: ='Cash Flow FY2'!B10 -> 0 | E41: ='Cash Flow FY3'!B10 -> 0 | F41: ='Cash Flow FY4'!B10 -> 0 | G41: ='Cash Flow FY5'!B10 -> 0 | H41: 600 | I41: 600
A42: Advertising | C42: ='Cash Flow FY1'!B12 -> 2000 | D42: ='Cash Flow FY2'!B11 -> 0 | E42: ='Cash Flow FY3'!B11 -> 0 | F42: ='Cash Flow FY4'!B11 -> 0 | G42: ='Cash Flow FY5'!B11 -> 0 | H42: =+G42*(100%+$B42) -> 0 | I42: =+H42*(100%+$B42) -> 0
A43: Accounting | C43: 1000 | D43: 1000 | E43: 1000 | F43: 1
A46: Total Expense | C46: =SUM(C32:C45) -> 87309.6 | D46: =SUM(D32:D45) -> 187436 | E46: =SUM(E32:E45) -> 190048.4 | F46: =SUM(F32:F45) -> 190657.4 | G46: =SUM(G32:G45) -> 193705 | H46: =SUM(H32:H42) -> 151272 | I46: =SUM(I32:I42) -> 152515
A47: Outgoings | C47: =SUM(C34:C39) -> 22997.2 | D47: =SUM(D34:D39) -> 41516 | E47: =SUM(E34:E39) -> 44128.4 | F47: =SUM(F34:F39) -> 45736.4 | G47: =SUM(G34:G39) -> 48785
A48: Net Cashflow | C48: =C30-C46 -> -18189.6 | D48: =D30-D46 -> -3836 | E48: =E30-E46 -> 6091.6 | F48: =F30-F46 -> 15892.6 | G48: =G30-G46 -> 23045 | H48: =H30-H46 -> -135072 | I48: =I30-I46 -> -132265
A49: Net operating Profit | C49: =C48+C32 -> 41122.8 | D49: =D48+D32 -> 112084 | E49: =E48+E32 -> 122011.6 | F49: =F48+F32 -> 131812.6 | G49: =G48+G32 -> 138965 | H49: =H48+H32 -> -19152 | I49: =I48+I32 -> -16345
A50: Cap Rate | D50: =+D49/C5 -> 0.040610145 | E50: =+E49/D5 -> 0.032108316 | F50: =+F49/E5 -> 0.033035739 | G50: =+G49/F5 -> 0.033169829 | H50: =+H49/G5 -> -0.0043537415 | I50: =+I49/H5 -> -0.0035387031
A54: Investor Returns
A55: Round 1 | B55: 0.42 | C55: =$B$55*C22 -> 0 | D55: =$B$55*D22 -> 226568.16 | E55: =$B$55*E22 -> 305051.04 | F55: =$B$55*F22 -> 387458.08 | G55: =$B$55*G22 -> 473985.5
A56: Round 2 | B56: 0.18 | C56: =$B$56*C22 -> 0 | D56: =$B$56*D22 -> 97100.64 | E56: =$B$56*E22 -> 130736.16 | F56: =$B$56*F22 -> 166053.46 | G56: =$B$56*G22 -> 203136.64
A58: Investor Returnsn%
A59: Round 1 | B59: 0.42 | C59: =C55/800000 -> 0 | D59: =D55/800000 -> 0.2832102 | E59: =E55/800000 -> 0.3813138 | F59: =F55/800000 -> 0.48432261 | G59: =G55/800000 -> 0.59248188
A60: Round 2 | B60: 0.18 | C60: =C56/450000 -> 0 | D60: =D56/450000 -> 0.2157792 | E60: =E56/450000 -> 0.2905248 | F60: =F56/450000 -> 0.3690077 | G60: =G56/450000 -> 0.45141477
A63: Profit Calculations
A64: Sale Price | C64: =C12+320000 -> 3502852 | D64: =D5 -> 3800000 | E64: =E5 -> 3990000 | F64: =F5 -> 4189500 | G64: =G5 -> 4398975
A65: Min Commission | B65: 0.02 | C65: =-$B$65*C64 -> -70057.04 | D65: =-$B$65*D64 -> -76000 | E65: =-$B$65*E64 -> -79800 | F65: =-$B$65*F64 -> -83790 | G65: =-$B$65*G64 -> -87979.5
A66: Closing costs | C66: -5000 | D66: -5000 | E66: -5000 | F66: -5000 | G66: -5000
A67: Loan Payable | C67: =-$C$14 -> -1932000 | D67: =-$C$14 -> -1932000 | E67: =-$C$14 -> -1932000 | F67: =-$C$14 -> -1932000 | G67: =-$C$14 -> -1932000
A68: Net Cash flow | C68: =C48 -> -18189.6 | D68: =D48 -> -3836 | E68: =E48 -> 6091.6 | F68: =F48 -> 15892.6 | G68: =G48 -> 23045
A70: Residue | C70: =SUM(C64:C68) -> 1477605.4 | D70: =SUM(D64:D68) -> 1783164 | E70: =SUM(E64:E68) -> 1979291.6 | F70: =SUM(F64:F68) -> 2184602.6 | G70: =SUM(G64:G68) -> 2397040.5
A71: Payback Investors Capital | C71: =-$C$15 -> -1199892 | D71: =-$C$15 -> -1199892 | E71: =-$C$15 -> -1199892 | F71: =-$C$15 -> -1199892 | G71: =-$C$15 -> -1199892
A73: Profit | C73: =SUM(C70:C72) -> 277713.36 | D73: =SUM(D70:D72) -> 583272 | E73: =SUM(E70:E72) -> 779399.6 | F73: =SUM(F70:F72) -> 984710.6 | G73: =SUM(G70:G72) -> 1197148.5
A74: Profit % | C74: =-C73/C71 -> 0.23144863 | D74: =-D73/D71 -> 0.48610375 | E74: =-E73/E71 -> 0.64955813 | F74: =-F73/F71 -> 0.82066603 | G74: =-G73/G71 -> 0.99771354
A75: IRR | C75: =C74/C1 -> 0.23144863 | D75: =D74/D1 -> 0.24305187 | E75: =E74/E1 -> 0.21651938 | F75: =F74/F1 -> 0.20516651 | G75: =G74/G1 -> 0.19954271
A77: Total - Investors Profit Share | B77: =M15 -> 0.60352941 | C77: =C73*$B$77 -> 167608.18 | D77: =D73*$B$77 -> 352021.81 | E77: =E73*$B$77 -> 470390.58 | F77: =F73*$B$77 -> 594301.81 | G77: =G73*$B$77 -> 722514.33
A78: Total Investor % | B78: =L15 -> 1199892 | C78: =C77/$B$78 -> 0.13968606 | D78: =D77/$B$78 -> 0.29337791 | E78: =E77/$B$78 -> 0.39202743 | F78: =F77/$B$78 -> 0.49529608 | G78: =G77/$B$78 -> 0.60214947
A79: Total Investor IRR % | C79: =C78/C1 -> 0.13968606 | D79: =D78/D1 -> 0.14668895 | E79: =E78/E1 -> 0.13067581 | F79: =F78/F1 -> 0.12382402 | G79: =G78/G1 -> 0.12042989 | H79: =H78/H1 -> 0 | I79: =I78/I1 -> 0
A81: Round 1 Investors | B81: 0.42 | C81: =C73*$B$81 -> 116639.61 | D81: =D73*$B$81 -> 244974.24 | E81: =E73*$B$81 -> 327347.83 | F81: =F73*$B$81 -> 413578.45 | G81: =G73*$B$81 -> 502802.37
A82: Round 2 Investors | B82: 0.18 | C82: =$B$82*C73 -> 49988.405 | D82: =$B$82*D73 -> 104988.96 | E82: =$B$82*E73 -> 140291.93 | F82: =$B$82*F73 -> 177247.91 | G82: =$B$82*G73 -> 215486.73
A83: Developer Profit Share | B83: =100%-B77 -> 0.39647059 | C83: =$B$83*C73 -> 110105.18 | D83: =$B$83*D73 -> 231250.19 | E83: =$B$83*E73 -> 309009.02 | F83: =$B$83*F73 -> 390408.79 | G83: =$B$83*G73 -> 474634.17
A85: Profit Returns % | B85: Investment
A86: Round 1 Investors | B86: =L13 -> 800000 | C86: =C81/$B$86 -> 0.14579951 | D86: =D81/$B$86 -> 0.3062178 | E86: =E81/$B$86 -> 0.40918479 | F86: =F81/$B$86 -> 0.51697306 | G86: =G81/$B$86 -> 0.62850296
A87: Round 2 Investors | B87: =L14 -> 399892 | C87: =C82/$B$87 -> 0.12500476 | D87: =D82/$B$87 -> 0.26254329 | E87: =E82/$B$87 -> 0.35082454 | F87: =F82/$B$87 -> 0.44323944 | G87: =G82/$B$87 -> 0.53886232
A89: Profit Returns % IRR | B89: Investment
A90: Round 1 Investors | B90: =L17 -> 0 | C90: =C86/C1 -> 0.14579951 | D90: =D86/D1 -> 0.1531089 | E90: =E86/E1 -> 0.13639493 | F90: =F86/F1 -> 0.12924327 | G90: =G86/G1 -> 0.12570059
A91: Round 2 Investors | B91: =L18 -> 0 | C91: =C87/C1 -> 0.12500476 | D91: =D87/D1 -> 0.13127164 | E91: =E87/E1 -> 0.11694151 | F91: =F87/F1 -> 0.11080986 | G91: =G87/G1 -> 0.10777246
A96: Graph
A97: Potential Exit Outcome for $200K Contribution in Round 2 Capital Raising
A99: Property Sale Price | B99: =+G5 -> 4398975
A100: Total Project Profit (minus costs) | B100: =G73 -> 1197148.5
A101: Investor Contribution Round 2 | B101: 200000
A102: Equity Share for $200K in round 2 | B102: =200000/450000*0.18 -> 0.08
A103: Return for $200K Contribution for Round 2 Investor | B103: =+B102*B100 -> 95771.88

Sheet Cash Flow FY1
A1: Expenses | C1: 46023 | D1: 46054 | E1: 46082 | F1: 46113 | G1: 46143 | H1: 46174
A2: Total | B2: =SUM(B3:B16) -> 86309.6 | C2: =SUM(C3:C16) -> 16616.533 | D2: =SUM(D3:D16) -> 14262.133 | E2: =SUM(E3:E16) -> 14607.733 | F2: =SUM(F3:F16) -> 14607.733 | G2: =SUM(G3:G16) -> 13107.733 | H2: =SUM(H3:H16) -> 13107.733
A3: Interest Payments | B3: =SUM(C3:H3) -> 59312.4 | C3: =+((2760000*70%)*6.14%)/12 -> 9885.4 | D3: =+((2760000*70%)*6.14%)/12 -> 9885.4 | E3: =+((2760000*70%)*6.14%)/12 -> 9885.4 | F3: =+((2760000*70%)*6.14%)/12 -> 9885.4 | G3: =+((2760000*70%)*6.14%)/12 -> 9885.4 | H3: =+((2760000*70%)*6.14%)/12 -> 9885.4
A4: Council Rates | B4: =SUM(C4:H4) -> 6350 | C4: =+(1270*10)/12 -> 1058.3333 | D4: =+(1270*10)/12 -> 1058.3333 | E4: =+(1270*10)/12 -> 1058.3333 | F4: =+(1270*10)/12 -> 1058.3333 | G4: =+(1270*10)/12 -> 1058.3333 | H4: =+(1270*10)/12 -> 1058.3333
A5: Insurance | B5: =SUM(C5:H5) -> 3000 | C5: 500 | D5: 500 | E5: 500 | F5: 500 | G5: 500 | H5: 500
A6: Landscaping | B6: =SUM(C6:H6) -> 1500 | D6: 300 | E6: 300 | F6: 300 | G6: 300 | H6: 300
A7: Repairs & Maintaince | B7: =SUM(C7:H7) -> 2500 | D7: 500 | E7: 500 | F7: 500 | G7: 500 | H7: 500
A8: Property Management 6% | B8: =SUM(C8:H8) -> 4147.2 | C8: =+C22*6% -> 172.8 | D8: =+D22*6% -> 518.4 | E8: =+E22*6% -> 864 | F8: =+F22*6% -> 864 | G8: =+G22*6% -> 864 | H8: =+H22*6% -> 864
A9: Leasing Fee 3% | B9: =SUM(C9:H9) -> 5500 | C9: 2200 | D9: 1100 | E9: 1100 | F9: 1100
A10: Land Tax | B10: =SUM(C10:H10) -> 0
A11: Letting Fee | B11: =SUM(C11:H11) -> 2000 | C11: =200*C20 -> 800 | D11: =200*(D20-C20) -> 400 | E11: =200*(E20-D20) -> 400 | F11: =200*(F20-E20) -> 400 | G11: =200*(G20-F20) -> 0 | H11: =200*(H20-G20) -> 0
A12: Advertising | B12: =SUM(C12:H12) -> 2000 | C12: 2000
B14: =SUM(C14:H14) -> 0
B15: =SUM(C15:H15) -> 0
B16: =SUM(C16:H16) -> 0
A18: Income
A19: Rent Per Unit | C19: 360 | D19: 360 | E19: 360 | F19: 360 | G19: 360 | H19: 360
A20: No. of Units Rented | C20: 4 | D20: 6 | E20: 8 | F20: 10 | G20: 10 | H20: 10
A21: No. Of weeks | B21: =SUM(C21:H21) -> 23 | C21: 2 | D21: 4 | E21: 5 | F21: 4 | G21: 4 | H21: 4
A22: Total Income | B22: =SUM(C22:H22) -> 69120 | C22: =+C19*C20*C21 -> 2880 | D22: =+D19*D20*D21 -> 8640 | E22: =+E19*E20*E21 -> 14400 | F22: =+F19*F20*F21 -> 14400 | G22: =+G19*G20*G21 -> 14400 | H22: =+H19*H20*H21 -> 14400
B23: =SUM(C23:H23) -> 0
B24: =SUM(C24:H24) -> 0
A25: Net Cash flow | B25: =B22-B2 -> -17189.6 | C25: =C22-C2 -> -13736.533 | D25: =D22-D2 -> -5622.1333 | E25: =E22-E2 -> -207.73333 | F25: =F22-F2 -> -207.73333 | G25: =G22-G2 -> 1292.2667 | H25: =H22-H2 -> 1292.2667

Sheet Cash Flow FY2
A1: Expenses | B1: Totals | C1: 46204 | D1: 46235 | E1: 46266 | F1: 46296 | G1: 46327 | H1: 46357 | I1: 46388 | J1: 46419 | K1: 46447 | L1: 46478 | M1: 46508 | N1: 46539
A2: Interest Payments | B2: =SUM(C2:N2) -> 115920 | C2: =+((2760000*70%)*6%)/12 -> 9660 | D2: =+((2760000*70%)*6%)/12 -> 9660 | E2: =+((2760000*70%)*6%)/12 -> 9660 | F2: =+((2760000*70%)*6%)/12 -> 9660 | G2: =+((2760000*70%)*6%)/12 -> 9660 | H2: =+((2760000*70%)*6%)/12 -> 9660 | I2: =+((2760000*70%)*6%)/12 -> 9660 | J2: =+((2760000*70%)*6%)/12 -> 9660 | ... N2: =+((2760000*70%)*6%)/12 -> 9660
A3: Council Rates | B3: =SUM(C3:N3) -> 12720 | C3: 1060 | D3: 1060 | E3: 1060 | F3: 1060 | G3: 1060 | H3: 1060 | I3: 1060 | J3: 1060 | K3: 1060 | L3: 1060 | M3: 1060 | N3: 1060
A4: Insurance | B4: =SUM(C4:N4) -> 6000 | C4: 500 | D4: 500 | E4: 500 | F4: 500 | G4: 500 | H4: 500 | I4: 500 | J4: 500 | K4: 500 | L4: 500 | M4: 500 | N4: 500
A5: Landscaping | B5: =SUM(C5:N5) -> 3600 | C5: 300 | D5: 300 | E5: 300 | F5: 300 | G5: 300 | H5: 300 | I5: 300 | J5: 300 | K5: 300 | L5: 300 | M5: 300 | N5: 300
A6: Repairs & Maintaince | B6: =SUM(C6:N6) -> 6180 | C6: =500*1.03 -> 515 | D6: =500*1.03 -> 515 | E6: =500*1.03 -> 515 | F6: =500*1.03 -> 515 | G6: =500*1.03 -> 515 | H6: =500*1.03 -> 515 | I6: =500*1.03 -> 515 | J6: =500*1.03 -> 515 | ... N6: =500*1.03 -> 515
A7: Property Management 6% | B7: =SUM(C7:N7) -> 11016 | C7: =+C21*6% -> 1080 | D7: =+D21*6% -> 864 | E7: =+E21*6% -> 1080 | F7: =+F21*6% -> 864 | G7: =+G21*6% -> 864 | H7: =+H21*6% -> 864 | I7: =+I21*6% -> 864 | J7: =+J21*6% -> 907.2 | ... N7: =+N21*6% -> 907.2
A8: Misc | B8: =SUM(C8:N8) -> 2000 | E8: 1000 | K8: 1000
A9: Land Tax | B9: =SUM(C9:N9) -> 29000 | M9: 29000
A10: Letting Fee | B10: =SUM(C10:N10) -> 0 | G10: =200*(G19-F19) -> 0 | H10: =200*(H19-G19) -> 0 | J10: =200*(J19-I19) -> 0 | K10: =200*(K19-J19) -> 0 | L10: =200*(L19-K19) -> 0 | M10: =200*(M19-L19) -> 0 | N10: =200*(N19-M19) -> 0
A11: Advertising | B11: =SUM(C11:N11) -> 0
B12: =SUM(C12:N12) -> 0
B14: =SUM(C14:N14) -> 0
A15: Total Expenses | B15: =SUM(B2:B14) -> 186436 | C15: =SUM(C2:C14) -> 13115 | D15: =SUM(D2:D14) -> 12899 | E15: =SUM(E2:E14) -> 14115 | F15: =SUM(F2:F14) -> 12899 | G15: =SUM(G2:G14) -> 12899 | H15: =SUM(H2:H14) -> 12899 | I15: =SUM(I2:I14) -> 12899 | ... N15: =SUM(N2:N14) -> 12942.2
A17: Income | B17: Increase | J17: 0.05
A18: Rent Per Unit | C18: 360 | D18: 360 | E18: 360 | F18: 360 | G18: 360 | H18: 360 | I18: 360 | J18: =+I18*(100%+J17) -> 378 | K18: =+J18*(100%+K17) -> 378 | L18: =+K18*(100%+L17) -> 378 | M18: =+L18*(100%+M17) -> 378 | N18: =+M18*(100%+N17) -> 378
A19: No. of Units Rented | C19: 10 | D19: 10 | E19: 10 | F19: 10 | G19: 10 | H19: 10 | I19: 10 | J19: 10 | K19: 10 | L19: 10 | M19: 10 | N19: 10
A20: No. Of weeks | B20: =SUM(C20:N20) -> 50 | C20: 5 | D20: 4 | E20: 5 | F20: 4 | G20: 4 | H20: 4 | I20: 4 | J20: 4 | K20: 4 | L20: 4 | M20: 4 | N20: 4
A21: Total Income | B21: =SUM(C21:N21) -> 183600 | C21: =+C18*C19*C20 -> 18000 | D21: =+D18*D19*D20 -> 14400 | E21: =+E18*E19*E20 -> 18000 | F21: =+F18*F19*F20 -> 14400 | G21: =+G18*G19*G20 -> 14400 | H21: =+H18*H19*H20 -> 14400 | I21: =+I18*I19*I20 -> 14400 | J21: =+J18*J19*J20 -> 15120 | ... N21: =+N18*N19*N20 -> 15120
A23: Net Cash flow | B23: =B21-B15 -> -2836 | C23: =C21-C15 -> 4885 | D23: =D21-D15 -> 1501 | E23: =E21-E15 -> 3885 | F23: =F21-F15 -> 1501 | G23: =G21-G15 -> 1501 | H23: =H21-H15 -> 1501 | I23: =I21-I15 -> 1501 | ... N23: =N21-N15 -> 2177.8

Sheet Cash Flow FY3
A1: Expenses | B1: Totals | C1: 46569 | D1: 46600 | E1: 46631 | F1: 46661 | G1: 46692 | H1: 46722 | I1: 46753 | J1: 46784 | K1: 46813 | L1: 46844 | M1: 46874 | N1: 46905
A2: Interest Payments | B2: =SUM(C2:N2) -> 115920 | C2: =+((2760000*70%)*6%)/12 -> 9660 | D2: =+((2760000*70%)*6%)/12 -> 9660 | E2: =+((2760000*70%)*6%)/12 -> 9660 | F2: =+((2760000*70%)*6%)/12 -> 9660 | G2: =+((2760000*70%)*6%)/12 -> 9660 | H2: =+((2760000*70%)*6%)/12 -> 9660 | I2: =+((2760000*70%)*6%)/12 -> 9660 | J2: =+((2760000*70%)*6%)/12 -> 9660 | ... N2: =+((2760000*70%)*6%)/12 -> 9660
A3: Council Rates | B3: =SUM(C3:N3) -> 12780 | C3: 1065 | D3: 1065 | E3: 1065 | F3: 1065 | G3: 1065 | H3: 1065 | I3: 1065 | J3: 1065 | K3: 1065 | L3: 1065 | M3: 1065 | N3: 1065
A4: Insurance | B4: =SUM(C4:N4) -> 7800 | C4: 650 | D4: 650 | E4: 650 | F4: 650 | G4: 650 | H4: 650 | I4: 650 | J4: 650 | K4: 650 | L4: 650 | M4: 650 | N4: 650
A5: Landscaping | B5: =SUM(C5:N5) -> 3600 | C5: 300 | D5: 300 | E5: 300 | F5: 300 | G5: 300 | H5: 300 | I5: 300 | J5: 300 | K5: 300 | L5: 300 | M5: 300 | N5: 300
A6: Repairs & Maintaince | B6: =SUM(C6:N6) -> 6180 | C6: =500*1.03 -> 515 | D6: =500*1.03 -> 515 | E6: =500*1.03 -> 515 | F6: =500*1.03 -> 515 | G6: =500*1.03 -> 515 | H6: =500*1.03 -> 515 | I6: =500*1.03 -> 515 | J6: =500*1.03 -> 515 | ... N6: =500*1.03 -> 515
A7: Property Management | B7: =SUM(C7:N7) -> 11768.4 | C7: =+C21*6% -> 1134 | D7: =+D21*6% -> 907.2 | E7: =+E21*6% -> 1158 | F7: =+F21*6% -> 926.4 | G7: =+G21*6% -> 926.4 | H7: =+H21*6% -> 926.4 | I7: =+I21*6% -> 926.4 | J7: =+J21*6% -> 972.72 | ... N7: =+N21*6% -> 972.72
A8: Misc | B8: =SUM(C8:N8) -> 2000 | E8: 1000 | K8: 1000
A9: Land Tax | B9: =SUM(C9:N9) -> 29000 | M9: 29000
A10: Letting Fee | B10: =SUM(C10:N10) -> 0
A11: Advertising | B11: =SUM(C11:N11) -> 0
B12: =SUM(C12:N12) -> 0
B14: =SUM(C14:N14) -> 0
A15: Total | B15: =SUM(B2:B14) -> 189048.4 | C15: =SUM(C2:C14) -> 13324 | D15: =SUM(D2:D14) -> 13097.2 | E15: =SUM(E2:E14) -> 14348 | F15: =SUM(F2:F14) -> 13116.4 | G15: =SUM(G2:G14) -> 13116.4 | H15: =SUM(H2:H14) -> 13116.4 | I15: =SUM(I2:I14) -> 13116.4 | ... N15: =SUM(N2:N14) -> 13162.72
B16: =SUM(C16:N16) -> 0
A17: Income | B17: =SUM(C17:N17) -> 0.05 | J17: 0.05
A18: Rent Per Unit | C18: ='Cash Flow FY2'!N18 -> 378 | D18: 378 | E18: 386 | F18: 386 | G18: 386 | H18: 386 | I18: 386 | J18: =+I18*(100%+J17) -> 405.3 | K18: =+J18*(100%+K17) -> 405.3 | L18: =+K18*(100%+L17) -> 405.3 | M18: =+L18*(100%+M17) -> 405.3 | N18: =+M18*(100%+N17) -> 405.3
A19: No. of Units Rented | C19: 10 | D19: 10 | E19: 10 | F19: 10 | G19: 10 | H19: 10 | I19: 10 | J19: 10 | K19: 10 | L19: 10 | M19: 10 | N19: 10
A20: No. Of weeks | B20: =SUM(C20:N20) -> 50 | C20: 5 | D20: 4 | E20: 5 | F20: 4 | G20: 4 | H20: 4 | I20: 4 | J20: 4 | K20: 4 | L20: 4 | M20: 4 | N20: 4
A21: Total Income | B21: =SUM(C21:N21) -> 196140 | C21: =+C18*C19*C20 -> 18900 | D21: =+D18*D19*D20 -> 15120 | E21: =+E18*E19*E20 -> 19300 | F21: =+F18*F19*F20 -> 15440 | G21: =+G18*G19*G20 -> 15440 | H21: =+H18*H19*H20 -> 15440 | I21: =+I18*I19*I20 -> 15440 | J21: =+J18*J19*J20 -> 16212 | ... N21: =+N18*N19*N20 -> 16212
B22: =SUM(C22:N22) -> 0
B23: =SUM(C23:N23) -> 0
A24: Net Cash flow | B24: =B21-B15 -> 7091.6 | C24: =C21-C15 -> 5576 | D24: =D21-D15 -> 2022.8 | E24: =E21-E15 -> 4952 | F24: =F21-F15 -> 2323.6 | G24: =G21-G15 -> 2323.6 | H24: =H21-H15 -> 2323.6 | I24: =I21-I15 -> 2323.6 | ... N24: =N21-N15 -> 3049.28

Sheet Cash Flow FY4
A1: Expenses | B1: Totals | C1: 46569 | D1: 46600 | E1: 46631 | F1: 46661 | G1: 46692 | H1: 46722 | I1: 46753 | J1: 46784 | K1: 46813 | L1: 46844 | M1: 46874 | N1: 46905
A2: Interest Payments | B2: =SUM(C2:N2) -> 115920 | C2: =+((2760000*70%)*6%)/12 -> 9660 | D2: =+((2760000*70%)*6%)/12 -> 9660 | E2: =+((2760000*70%)*6%)/12 -> 9660 | F2: =+((2760000*70%)*6%)/12 -> 9660 | G2: =+((2760000*70%)*6%)/12 -> 9660 | H2: =+((2760000*70%)*6%)/12 -> 9660 | I2: =+((2760000*70%)*6%)/12 -> 9660 | J2: =+((2760000*70%)*6%)/12 -> 9660 | ... N2: =+((2760000*70%)*6%)/12 -> 9660
A3: Council Rates | B3: =SUM(C3:N3) -> 13163.4 | C3: =1065*1.03 -> 1096.95 | D3: =1065*1.03 -> 1096.95 | E3: =1065*1.03 -> 1096.95 | F3: =1065*1.03 -> 1096.95 | G3: =1065*1.03 -> 1096.95 | H3: =1065*1.03 -> 1096.95 | I3: =1065*1.03 -> 1096.95 | J3: =1065*1.03 -> 1096.95 | ... N3: =1065*1.03 -> 1096.95
A4: Insurance | B4: =SUM(C4:N4) -> 8400 | C4: 700 | D4: 700 | E4: 700 | F4: 700 | G4: 700 | H4: 700 | I4: 700 | J4: 700 | K4: 700 | L4: 700 | M4: 700 | N4: 700
A5: Landscaping | B5: =SUM(C5:N5) -> 3600 | C5: 300 | D5: 300 | E5: 300 | F5: 300 | G5: 300 | H5: 300 | I5: 300 | J5: 300 | K5: 300 | L5: 300 | M5: 300 | N5: 300
A6: Repairs & Maintaince | B6: =SUM(C6:N6) -> 6180 | C6: =500*1.03 -> 515 | D6: =500*1.03 -> 515 | E6: =500*1.03 -> 515 | F6: =500*1.03 -> 515 | G6: =500*1.03 -> 515 | H6: =500*1.03 -> 515 | I6: =500*1.03 -> 515 | J6: =500*1.03 -> 515 | ... N6: =500*1.03 -> 515
A7: Property Management | B7: =SUM(C7:N7) -> 12393 | C7: =+C21*6% -> 1215 | D7: =+D21*6% -> 972 | E7: =+E21*6% -> 1215 | F7: =+F21*6% -> 972 | G7: =+G21*6% -> 972 | H7: =+H21*6% -> 972 | I7: =+I21*6% -> 972 | J7: =+J21*6% -> 1020.6 | ... N7: =+N21*6% -> 1020.6
A8: Misc | B8: =SUM(C8:N8) -> 2000 | E8: 1000 | K8: 1000
A9: Land Tax | B9: =SUM(C9:N9) -> 29000 | M9: 29000
A10: Letting Fee | B10: =SUM(C10:N10) -> 0
A11: Advertising | B11: =SUM(C11:N11) -> 0
B12: =SUM(C12:N12) -> 0
B14: =SUM(C14:N14) -> 0
A15: Total | B15: =SUM(B2:B14) -> 190656.4 | C15: =SUM(C2:C14) -> 13486.95 | D15: =SUM(D2:D14) -> 13243.95 | E15: =SUM(E2:E14) -> 14486.95 | F15: =SUM(F2:F14) -> 13243.95 | G15: =SUM(G2:G14) -> 13243.95 | H15: =SUM(H2:H14) -> 13243.95 | I15: =SUM(I2:I14) -> 13243.95 | ... N15: =SUM(N2:N14) -> 13292.55
B16: =SUM(C16:N16) -> 0
A17: Income | B17: =SUM(C17:N17) -> 0.05 | J17: 0.05
A18: Rent Per Unit | C18: 405 | D18: 405 | E18: 405 | F18: 405 | G18: 405 | H18: 405 | I18: 405 | J18: =+I18*(100%+J17) -> 425.25 | K18: =+J18*(100%+K17) -> 425.25 | L18: =+K18*(100%+L17) -> 425.25 | M18: =+L18*(100%+M17) -> 425.25 | N18: =+M18*(100%+N17) -> 425.25
A19: No. of Units Rented | C19: 10 | D19: 10 | E19: 10 | F19: 10 | G19: 10 | H19: 10 | I19: 10 | J19: 10 | K19: 10 | L19: 10 | M19: 10 | N19: 10
A20: No. Of weeks | B20: =SUM(C20:N20) -> 50 | C20: 5 | D20: 4 | E20: 5 | F20: 4 | G20: 4 | H20: 4 | I20: 4 | J20: 4 | K20: 4 | L20: 4 | M20: 4 | N20: 4
A21: Total Income | B21: =SUM(C21:N21) -> 206550 | C21: =+C18*C19*C20 -> 20250 | D21: =+D18*D19*D20 -> 16200 | E21: =+E18*E19*E20 -> 20250 | F21: =+F18*F19*F20 -> 16200 | G21: =+G18*G19*G20 -> 16200 | H21: =+H18*H19*H20 -> 16200 | I21: =+I18*I19*I20 -> 16200 | J21: =+J18*J19*J20 -> 17010 | ... N21: =+N18*N19*N20 -> 17010
B22: =SUM(C22:N22) -> 0
B23: =SUM(C23:N23) -> 0
A24: Net Cash flow | B24: =B21-B15 -> 15893.6 | C24: =C21-C15 -> 6763.05 | D24: =D21-D15 -> 2956.05 | E24: =E21-E15 -> 5763.05 | F24: =F21-F15 -> 2956.05 | G24: =G21-G15 -> 2956.05 | H24: =H21-H15 -> 2956.05 | I24: =I21-I15 -> 2956.05 | ... N24: =N21-N15 -> 3717.45

Sheet Cash Flow FY5
A1: Expenses | B1: Totals | C1: 46569 | D1: 46600 | E1: 46631 | F1: 46661 | G1: 46692 | H1: 46722 | I1: 46753 | J1: 46784 | K1: 46813 | L1: 46844 | M1: 46874 | N1: 46905
A2: Interest Payments | B2: =SUM(C2:N2) -> 115920 | C2: =+((2760000*70%)*6%)/12 -> 9660 | D2: =+((2760000*70%)*6%)/12 -> 9660 | E2: =+((2760000*70%)*6%)/12 -> 9660 | F2: =+((2760000*70%)*6%)/12 -> 9660 | G2: =+((2760000*70%)*6%)/12 -> 9660 | H2: =+((2760000*70%)*6%)/12 -> 9660 | I2: =+((2760000*70%)*6%)/12 -> 9660 | J2: =+((2760000*70%)*6%)/12 -> 9660 | ... N2: =+((2760000*70%)*6%)/12 -> 9660
A3: Council Rates | B3: =SUM(C3:N3) -> 15600 | C3: 1300 | D3: 1300 | E3: 1300 | F3: 1300 | G3: 1300 | H3: 1300 | I3: 1300 | J3: 1300 | K3: 1300 | L3: 1300 | M3: 1300 | N3: 1300
A4: Insurance | B4: =SUM(C4:N4) -> 8400 | C4: 700 | D4: 700 | E4: 700 | F4: 700 | G4: 700 | H4: 700 | I4: 700 | J4: 700 | K4: 700 | L4: 700 | M4: 700 | N4: 700
A5: Landscaping | B5: =SUM(C5:N5) -> 3600 | C5: 300 | D5: 300 | E5: 300 | F5: 300 | G5: 300 | H5: 300 | I5: 300 | J5: 300 | K5: 300 | L5: 300 | M5: 300 | N5: 300
A6: Repairs & Maintaince | B6: =SUM(C6:N6) -> 6180 | C6: =500*1.03 -> 515 | D6: =500*1.03 -> 515 | E6: =500*1.03 -> 515 | F6: =500*1.03 -> 515 | G6: =500*1.03 -> 515 | H6: =500*1.03 -> 515 | I6: =500*1.03 -> 515 | J6: =500*1.03 -> 515 | ... N6: =500*1.03 -> 515
A7: Property Management | B7: =SUM(C7:N7) -> 13005 | C7: =+C21*6% -> 1275 | D7: =+D21*6% -> 1020 | E7: =+E21*6% -> 1275 | F7: =+F21*6% -> 1020 | G7: =+G21*6% -> 1020 | H7: =+H21*6% -> 1020 | I7: =+I21*6% -> 1020 | J7: =+J21*6% -> 1071 | ... N7: =+N21*6% -> 1071
A8: Misc | B8: =SUM(C8:N8) -> 2000 | E8: 1000 | K8: 1000
A9: Land Tax | B9: =SUM(C9:N9) -> 29000 | M9: 29000
A10: Letting Fee | B10: =SUM(C10:N10) -> 0
A11: Advertising | B11: =SUM(C11:N11) -> 0
B12: =SUM(C12:N12) -> 0
B14: =SUM(C14:N14) -> 0
A15: Total | B15: =SUM(B2:B14) -> 193705 | C15: =SUM(C2:C14) -> 13750 | D15: =SUM(D2:D14) -> 13495 | E15: =SUM(E2:E14) -> 14750 | F15: =SUM(F2:F14) -> 13495 | G15: =SUM(G2:G14) -> 13495 | H15: =SUM(H2:H14) -> 13495 | I15: =SUM(I2:I14) -> 13495 | ... N15: =SUM(N2:N14) -> 13546
B16: =SUM(C16:N16) -> 0
A17: Income | B17: =SUM(C17:N17) -> 0.05 | J17: 0.05
A18: Rent Per Unit | C18: 425 | D18: 425 | E18: 425 | F18: 425 | G18: 425 | H18: 425 | I18: 425 | J18: =+I18*(100%+J17) -> 446.25 | K18: =+J18*(100%+K17) -> 446.25 | L18: =+K18*(100%+L17) -> 446.25 | M18: =+L18*(100%+M17) -> 446.25 | N18: =+M18*(100%+N17) -> 446.25
A19: No. of Units Rented | C19: 10 | D19: 10 | E19: 10 | F19: 10 | G19: 10 | H19: 10 | I19: 10 | J19: 10 | K19: 10 | L19: 10 | M19: 10 | N19: 10
A20: No. Of weeks | B20: =SUM(C20:N20) -> 50 | C20: 5 | D20: 4 | E20: 5 | F20: 4 | G20: 4 | H20: 4 | I20: 4 | J20: 4 | K20: 4 | L20: 4 | M20: 4 | N20: 4
A21: Total Income | B21: =SUM(C21:N21) -> 216750 | C21: =+C18*C19*C20 -> 21250 | D21: =+D18*D19*D20 -> 17000 | E21: =+E18*E19*E20 -> 21250 | F21: =+F18*F19*F20 -> 17000 | G21: =+G18*G19*G20 -> 17000 | H21: =+H18*H19*H20 -> 17000 | I21: =+I18*I19*I20 -> 17000 | J21: =+J18*J19*J20 -> 17850 | ... N21: =+N18*N19*N20 -> 17850
B22: =SUM(C22:N22) -> 0
B23: =SUM(C23:N23) -> 0
A24: Net Cash flow | B24: =B21-B15 -> 23045 | C24: =C21-C15 -> 7500 | D24: =D21-D15 -> 3505 | E24: =E21-E15 -> 6500 | F24: =F21-F15 -> 3505 | G24: =G21-G15 -> 3505 | H24: =H21-H15 -> 3505 | I24: =I21-I15 -> 3505 | ... N24: =N21-N15 -> 4304

Sheet 2 x Land Sales@ 80 LVR
A1: Feasibility
A2: Size of each unit | B2: Sqs | C2: 0 | F2: Money Partners | AA2: Settlement
A3: Total Build area in Sqm | B3: Sqm | C3: =+C2*9.29*C5 -> 0 | G3: Loan# | H3: Amt | I3: Month Loaned | J3: No. of Month | K3: Interest rate | L3: Interest | M3: Total Amt | AA3: May
A4: Land area in sqm | C4: 1295 | F4: Sharath | G4: 1 | H4: 70000 | I4: 45717 | J4: 15 | K4: 0.15 | L4: =(J4/12)*(H4*K4) -> 13125
A5: No of Dwellings | C5: 2 | E5: Sell per Sq M | G5: 2 | H5: =200000-H4 -> 130000 | I5: 45992 | J5: 5 | K5: 0.15 | L5: =(J5/12)*(H5*K5) -> 8125 | M5: =SUM(L4:L5) -> 21250
A6: Avg Dwellings sell price | B6: 2430 | C6: =+(1750000+1800000)/2 -> 1775000 | E6: =C8/C4 -> 2741.3127 | G6: Total | H6: =SUM(H4:H5) -> 200000
A8: Total Sales | C8: =C6*C5+C7 -> 3550000 | F8: Vivek | G8: 1 | H8: 70000 | I8: 45748 | J8: 15 | K8: 0.15 | L8: =(J8/12)*(H8*K8) -> 13125
A9: GST on margin scheme | G9: 2 | H9: 100000 | I9: 46023 | J9: 5 | K9: 0.15 | L9: =(J9/12)*(H9*K9) -> 6250
A10: Total Revenue | B10: =C10/C10 -> 1 | C10: =+C8+C9 -> 3550000 | G10: 3 | H10: =400000-H9-H8 -> 230000 | I10: 46023 | J10: 5 | K10: 0.15 | L10: =(J10/12)*(H10*K10) -> 14375 | M10: =SUM(L8:L10) -> 33750
A11: All costs are GST exclusive | E11: Cost per Sqm | G11: Total | H11: =SUM(H8:H10) -> 400000
A12: Purchase price | B12: =+C12/C10 -> 0.77746479 | C12: 2760000 | E12: =+C12/C4 -> 2131.2741 | F12: Total Capital | H12: =+H6+H11 -> 600000
A13: Stamp duty + buy in Fees | B13: 0.06 | C13: =(C12+C11)*B13 -> 165600
A14: Finders Fee | C14: 40000 | F14: Ramakanth | G14: 1 | H14: 150000 | I14: 46023 | J14: 5 | K14: 0.15 | L14: =(J14/12)*(H14*K14) -> 9375 | M14: =+L14 -> 9375
A15: Accounting & Legals | C15: 13000 | F15: Investor 4 | G15: 1 | H15: 250000 | I15: 46023 | J15: 5 | K15: 0.15 | L15: =(J15/12)*(H15*K15) -> 15625 | M15: =+L15 -> 15625
A16: Funding cost establishment cost | C16: ='Senior Funding Model'!C20 -> 28223.8
A17: Acquisition cost | B17: =C17/C10 -> 0.84699262 | C17: =SUM(C11:C16) -> 3006823.8
A18: Due Dilligence | B18: 0.33 | C18: 0 | F18: Capital amt | H18: =+H12+H14+H15 -> 1000000 | K18: Total Interest | L18: =SUM(L4:L17) -> 80000
A19: Utilities | B19: 0.01 | C19: 50000
B20: 0.008 | F20: Senior Debt | G20: 1 | H20: =E28 -> 2208000 | I20: 46023 | J20: 5 | K20: 0.08 | L20: =(J20/12)*(H20*K20) -> 73600
A21: Marketing & selling cost | B21: 0.015 | C21: =$C$10*B21 -> 53250
A22: Holding Cost | C22: 5000 | F22: Total | H22: =H20+H18 -> 3208000 | J22: Total Funding Cost | L22: =+L20+L18 -> 153600
A23: Demo | C23: 60000 | F23: Net Cashflow
A24: Misc cost
A26: Total Development Cost | B26: =C26/C10 -> 0.047394366 | C26: =SUM(C18:C25) -> 168250 | R26: Burn Rate | T26: Amt | U26: Rate | V26: Per month
A27: Total Project Cost before funding | C27: =C17+C26 -> 3175073.8 | E27: Loan | F27: Cash required | R27: Senior Debt | T27: =H20 -> 2208000 | U27: =K20 -> 0.08 | V27: =T27*U27/12 -> 14720
A28: Profit Before Funding cost | B28: =+C28/C27 -> 0.11808425 | C28: =+C10-C27 -> 374926.2 | E28: =C12*80% -> 2208000 | F28: =+C17-E28+C19+C23+C22+C16 -> 942047.6 | R28: Private | T28: 1000000 | U28: 0.15 | V28: =U28*T28/12 -> 12500
A29: Funding Cost w/ money partners | B29: =+C29/C8 -> 0.043267606 | C29: =L22 -> 153600 | I29: =+#REF!/C6 -> #REF! | T29: Total | V29: =SUM(V27:V28) -> 27220
A30: JV Partners cost | B30: =+C30/C8 -> 0.020732394 | C30: =+G52 -> 73600 | T30: Per block per month | V30: =V29/2 -> 13610
A32: Profit After Money Partners Funding | B32: =+C32/C27 -> 0.069707419 | C32: =C28-C29 -> 221326.2
A33: Profit After JV partners | B33: =C33/C27 -> 0.094903684 | C33: =C28-C30 -> 301326.2
A34: Funding
A35: Private | B35: 800000 | C35: =+((B35*12%)/12)*5 -> 40000
A36: Mortgage | B36: 10000 | C36: 50000
C37: =SUM(C35:C36) -> 90000
C41: JV money | D41: Money Partners | E41: Share | F41: Interest Rate | G41: Return JV | H41: MP
A42: Sharath | C42: =H6 -> 200000 | E42: =+((C42/850000)*0.45)*100% -> 0.10588235 | F42: 0.2 | G42: =C42*$C$76 -> 0 | I42: =(C42*F42/12)*3 -> 10000
A43: Vivek | C43: =H11 -> 400000 | E43: =+((C43/850000)*0.45)*100% -> 0.21176471 | F43: 0.2 | G43: =C43*$C$76 -> 0 | I43: =(C43*F43/12)*3 -> 20000
A44: Vijay | C44: 200000 | E44: =+((C44/850000)*0.45)*100% -> 0.10588235 | F44: 0.2 | G44: =C44*$C$76 -> 0 | I44: =(C44*F44/12)*3 -> 10000
A45: xxxx | E45: =+((C45/850000)*0.45)*100% -> 0
A46: \ | F46: 0.15 | H46: =(D46*F46/12)*3 -> 0
A47: Money Partner 5 | F47: 0.15 | H47: =(D47*F47/12)*3 -> 0
A48: Ramakanth 6 | D48: =+H14 -> 150000 | F48: 0.15 | H48: =M14 -> 9375 | I48: =M14 -> 9375
A50: Total | C50: =SUM(C42:C48) -> 800000 | D50: =SUM(D42:D48) -> 150000 | E50: =SUM(E42:E47) -> 0.42352941 | G50: =SUM(G42:G47) -> 0 | H50: =SUM(H42:H48) -> 9375 | I50: =SUM(I42:I49) -> 49375
A51: Senior Debt | C51: =+H20 -> 2208000 | G51: =L20 -> 73600
A52: Total | C52: =+C50+C51 -> 3008000 | G52: =+G50+G51 -> 73600
A56: Stage 1
A57: Sale of Block 44 | B57: =C6 -> 1775000
A58: Minus Comissions | B58: =-B57*1.5% -> -26625
A59: Margin Scheme | B59: =-(B57-($C$12/2))*10% -> -39500
A60: Closing Costs | B60: -5000
A61: Loan payable | B61: =-1670000-9125-13253-2647-8850 -> -1703875
A62: Balance | B62: =SUM(B57:B61) -> 0
A64: Balance of loan | B64: =C51+B61 -> 504125
A66: Stage 2
A67: Sell block 2 | B67: 1800000
A68: Selling cost | B68: =-B67*1.5% -> -27000
A69: Minus Marin Scheme | B69: =-(B67-($C$12/2))*10% -> -42000
A70: Closing Costs | B70: -5000
A71: Loan Payable | B71: =-B64 -> -504125
A73: Residue | B73: =SUM(B67:B72) -> 1221875
A75: Balance after repaying Invesrtor Money | B75: =B73-C50-D50 -> 271875
A76: Profit before share for Investors | B76: =B75*E50 -> 115147.06
A77: Profit Share for Developer | B77: =B75-B76-H50 -> 147352.94
A78: Pay Interest repayments | B78: =-SUM(H46:H48) -> -9375

Sheet IM Presentaion
A1: Financial Year | B1: 1 (6 Months) | C1: 2 | D1: 3 | E1: 4 | F1: 5
A2: Year | B2: 2026 | C2: 2027 | D2: 2028 | E2: 2029 | F2: 2030
A3: Capital Growth | C3: 0.23188406 | D3: 0.05 | E3: 0.05 | F3: 0.05
A4: Property Valuation | B4: 2760000 | C4: 3400000 | D4: 3570000 | E4: 3748500 | F4: 3935925
A7: Rental Income Growth | C7: 0.025641026 | D7: 0.048780488 | E7: 0.046511628 | F7: 0.044444444
A8: No of unit available for rent | B8: 10 | C8: 10 | D8: 10 | E8: 10 | F8: 10
A9: Average Rent per unit | B9: 380 | C9: 390 | D9: 410 | E9: 430 | F9: 450
A10: No. of weeks | B10: 20 | C10: 50 | D10: 50 | E10: 50 | F10: 50
A11: Cash Flow
A12: Annual Rental Income | B12: 76000 | C12: 195000 | D12: 205000 | E12: 215000 | F12: 225000
A13: Expenes
A14: Council Rates | B14: 6350 | C14: 12720 | D14: 12780 | E14: 13163.4 | F14: 13558.92
A15: Insurance | B15: 2500 | C15: 5000 | D15: 5500 | E15: 6000 | F15: 6500
A16: Repairs & Maintaince | B16: 2000 | C16: 6180 | D16: 7000 | E16: 7500 | F16: 8000
A17: Property Management Fee | B17: 4032 | C17: 10710 | D17: 11811.6 | E17: 12393 | F17: 13005
A18: Misc | B18: 5000 | C18: 2500 | D18: 3000 | E18: 3500 | F18: 4000
A19: Land Tax | B19: 0 | C19: 29500 | D19: 30000 | E19: 30500 | F19: 31000
A20: Letting Fee | B20: 2000 | C20: 1000 | D20: 1000 | E20: 1000 | F20: 1000
A21: Advertising | B21: 2000 | C21: 0 | D21: 0 | E21: 0
A22: Total Expense | B22: 23882 | C22: 67610 | D22: 71091.6 | E22: 74056.4 | F22: 77063.92
A23: Net operating Profit | B23: 52118 | C23: 127390 | D23: 133908.4 | E23: 140943.6 | F23: 147936.08
A24: Interest Only Payments for 70% LVR @ 6% | B24: 57960 | C24: 115920 | D24: 115920 | E24: 115920 | F24: 115920
A25: Net Cashflow | B25: -5842 | C25: 11470 | D25: 17988.4 | E25: 25023.6 | F25: 32016.08
A26: Net Yield / Cap Rate | B26: 0.037766667 | C26: 0.074935294 | D26: 0.075018711 | E26: 0.0752 | F26: 0.075172205

Sheet Claro Clash flow
A2: Cashflow | C2: 1 | D2: 2 | E2: 3 | F2: 4 | G2: 5
A3: Rental Growth | D3: 0.05 | E3: 0.05 | F3: 0.05 | G3: 0.05 | H3: =(H5/G5)-100% -> -0.90507279 | I3: =(I5/H5)-100% -> 0.25
A4: Rent per unit per week | C4: 270 | D4: =+C4*(100%+D3) -> 283.5 | E4: =+D4*(100%+E3) -> 297.675 | F4: =+E4*(100%+F3) -> 312.55875 | G4: =+F4*(100%+G3) -> 328.18669
A5: Rev | C5: =+C4*10*52 -> 140400 | D5: =+D4*10*52 -> 147420 | E5: =+E4*10*52 -> 154791 | F5: =+F4*10*52 -> 162530.55 | G5: =+G4*10*52 -> 170657.08 | H5: ='Cash Flow FY4'!D21 -> 16200 | I5: ='Cash Flow FY4'!E21 -> 20250
A6: Expenes | B6: Yield | C6: =C5/2760000 -> 0.050869565 | D6: =D5/2760000 -> 0.053413043 | E6: =E5/2760000 -> 0.056083696 | F6: =F5/2760000 -> 0.05888788 | G6: =G5/2760000 -> 0.061832274
A7: Interest Payments | B7: 0.065 | C7: =(2760000*70%*$B7) -> 125580 | D7: =(2760000*70%*$B7) -> 125580 | E7: =(2760000*70%*$B7) -> 125580 | F7: =(2760000*70%*$B7) -> 125580 | G7: =(2760000*70%*$B7) -> 125580 | H7: =+G7*(100%+$B$7) -> 133742.7 | I7: =+H7*(100%+$B$7) -> 142435.98
H8: =+G18*(100%+$B18) -> 8400 | I8: =+H8*(100%+$B18) -> 8400
A10: Total Expenses | C10: =SUM(C7:C9) -> 125580 | D10: =SUM(D7:D9) -> 125580 | E10: =SUM(E7:E9) -> 125580 | F10: =SUM(F7:F9) -> 125580 | G10: =SUM(G7:G9) -> 125580
A11: Net Cashflow | C11: =+C5-C10 -> 14820 | D11: =+D5-D10 -> 21840 | E11: =+E5-E10 -> 29211 | F11: =+F5-F10 -> 36950.55 | G11: =+G5-G10 -> 45077.078
L12: 70% LVR on Value | M12: =70%*M15 -> 1932000 | N12: =N15*70% -> 2240000 | P12: =P15*70% -> 2450000 | R12: =R15*70% -> 2800000 | T12: =T15*70% -> 3150000 | U12: =U15*70% -> 3500000
A13: Outgoings | L13: Yr | N13: 1 | P13: 2 | R13: 3 | T13: 5 | U13: 6
A14: Council Rates | C14: 12720 | D14: 12720 | E14: 12780 | F14: 13163.4 | G14: 15600 | H14: =+G14*(100%+$B14) -> 15600 | I14: =+H14*(100%+$B14) -> 15600 | L14: Equity | M14: 850000 | N14: 850000 | P14: 850000 | R14: 850000 | T14: 850000 | U14: 850000
A15: Landscaping | C15: =300*12 -> 3600 | D15: =300*12 -> 3600 | E15: =300*12 -> 3600 | F15: =300*12 -> 3600 | G15: =300*12 -> 3600 | H15: =+G15*(100%+$B15) -> 3600 | I15: =+H15*(100%+$B15) -> 3600 | L15: Site valuation | M15: 2760000 | N15: 3200000 | P15: 3500000 | R15: 4000000 | T15: 4500000 | U15: 5000000
A16: Repairs & Maintaince | C16: 5000 | D16: 5000 | E16: 5000 | F16: 6180 | G16: 6180 | H16: =+G16*(100%+$B16) -> 6180 | I16: =+H16*(100%+$B16) -> 6180 | L16: Equity | M16: 0.45 | N16: 0.45 | P16: 0.45 | R16: 0.45 | T16: 0.45 | U16: 0.45
A17: ESM & AESMR | C17: =+(200*12)+1000 -> 3400 | D17: =+(200*12)+1000 -> 3400 | E17: =+(200*12)+1000 -> 3400 | F17: =+(200*12)+1000 -> 3400 | G17: =+(200*12)+1000 -> 3400 | H17: ='Cash Flow FY4'!D7 -> 972 | I17: ='Cash Flow FY4'!E7 -> 1215 | L17: share in the deal | M17: =M16*M15 -> 1242000 | N17: =N16*N15 -> 1440000 | P17: =P16*P15 -> 1575000 | R17: =R16*R15 -> 1800000 | T17: =T16*T15 -> 2025000 | U17: =U16*U15 -> 2250000
A18: Insurance | C18: 12000 | D18: 12000 | E18: 7800 | F18: 8400 | G18: 8400 | H18: ='Cash Flow FY4'!D8 -> 0 | I18: ='Cash Flow FY4'!E8 -> 1000 | L18: LVR 70% | M18: =M15*70% -> 1932000 | N18: =M18 -> 1932000 | P18: =N18 -> 1932000 | R18: =P18 -> 1932000 | T18: =R18 -> 1932000 | U18: =T18 -> 1932000
H19: =+(200*12)+1000 -> 3400 | I19: =+(200*12)+1000 -> 3400 | L19: Residue | M19: =M15-M18 -> 828000 | N19: =N15-N18 -> 1268000 | P19: =P15-P18 -> 1568000 | R19: =R15-R18 -> 2068000 | T19: =T15-T18 -> 2568000 | U19: =U15-U18 -> 3068000
A20: LandTax | C20: Excempt | D20: Excempt | E20: Excempt | F20: Excempt | G20: Excempt | H20: 600 | I20: 600 | L20: Closing costs incd taxes | M20: =165000+(2%*M15) -> 220200 | N20: =165000+(2%*N15) -> 229000 | P20: =165000+(2%*P15) -> 235000 | R20: =165000+(2%*R15) -> 245000 | T20: =165000+(2%*T15) -> 255000 | U20: =165000+(2%*U15) -> 265000
A21: Misc | C21: 2000 | D21: 2000 | E21: 2000 | F21: 2000 | G21: 2000 | H21: =+G20*(100%+$B20) -> #VALUE! | I21: =+H21*(100%+$B20) -> #VALUE! | L21: Equity left | M21: =M19-M20 -> 607800 | N21: =N19-N20 -> 1039000 | P21: =P19-P20 -> 1333000 | R21: =R19-R20 -> 1823000 | T21: =T19-T20 -> 2313000 | U21: =U19-U20 -> 2803000
A22: Property Management | H22: 10000 | I22: 10000 | L22: Equity paid out | M22: =IF(M21>M14,M14,M21) -> 607800 | N22: =IF(N21>N14,N14,N21) -> 850000 | P22: =IF(P21>P14,P14,P21) -> 850000 | R22: =IF(R21>R14,R14,R21) -> 850000 | T22: =IF(T21>T14,T14,T21) -> 850000 | U22: =IF(U21>U14,U14,U21) -> 850000
A23: Total out goings | C23: =+SUM(C14:C22) -> 38720 | D23: =+SUM(D14:D22) -> 38720 | E23: =+SUM(E14:E22) -> 34580 | F23: =+SUM(F14:F22) -> 36743.4 | G23: =+SUM(G14:G22) -> 39180 | H23: =SUM(H7:H22) -> #VALUE! | I23: =SUM(I7:I22) -> #VALUE! | L23: Profit | M23: =IF(M21>M14,(M21-M22),(M22-M14)) -> -242200 | N23: =IF(N21>N14,(N21-N22),(N22-N14)) -> 189000 | P23: =IF(P21>P14,(P21-P22),(P22-P14)) -> 483000 | R23: =IF(R21>R14,(R21-R22),(R22-R14)) -> 973000 | T23: =IF(T21>T14,(T21-T22),(T22-T14)) -> 1463000 | U23: =IF(U21>U14,(U21-U22),(U22-U14)) -> 1953000
A24: Expense per unit | C24: =+C23/10 -> 3872 | D24: =+D23/10 -> 3872 | E24: =+E23/10 -> 3458 | F24: =+F23/10 -> 3674.34 | G24: =+G23/10 -> 3918 | L24: Investor share | M24: =IF(M23>0,(M23*M16),M23) -> -242200 | N24: =IF(N23>0,(N23*N16),N23) -> 85050 | P24: =IF(P23>0,(P23*P16),P23) -> 217350 | R24: =IF(R23>0,(R23*R16),R23) -> 437850 | T24: =IF(T23>0,(T23*T16),T23) -> 658350 | U24: =IF(U23>0,(U23*U16),U23) -> 878850
H25: =H5-H23 -> #VALUE! | I25: =I5-I23 -> #VALUE! | L25: Investor Return | M25: =M24/M14 -> -0.28494118 | N25: =N24/N14 -> 0.10005882 | P25: =P24/P14 -> 0.25570588 | R25: =R24/R14 -> 0.51511765 | T25: =T24/T14 -> 0.77452941 | U25: =U24/U14 -> 1.0339412
L26: Annual Return | M26: =IF(M24>0,M23-M25,0) -> 0 | N26: =N25/N13 -> 0.10005882 | P26: =P25/P13 -> 0.12785294 | R26: =R25/R13 -> 0.17170588 | T26: =T25/T13 -> 0.15490588 | U26: =U25/U13 -> 0.17232353
L27: Krishna Return
C28: 45748 | D28: 46023
A29: Stage 1 Funding | C29: Stage 1 | D29: Stage 2
A30: Total | C30: =SUM(C31:C35) -> #REF! | D30: =SUM(D31:D39) -> #REF!
A31: Due Dilligence | C31: 5000
A32: Deposit | C32: 100000
A33: Finders Fee | C33: =#REF! -> #REF!
A34: Equity | D34: =2760000*20%-C32 -> 452000
A35: Spamp Duty | D35: =#REF! -> #REF!
A36: Reno/ Repairs | D36: =#REF! -> #REF!
A37: Closing costs | D37: 3000
D41: =+C48+E48 -> 73054
A42: Proposed | D42: =140000-D41 -> 66946
A44: Units | B44: SDA Basic | C44: RRC | D44: SDA + RRC | E44: OOA Lease | F44: Total w/ SDA | G44: Total w/o SDA | H44: 50% SDA Scenario | I44: Landlord Share (92%) Full SDA | J44: Landlord Share (92%) @ 50% SDA | K44: 50% SDA @ 16% | L44: 100% SDA @16% | M44: 16% Fee
A45: 1 | B45: 12180 | C45: 11858 | D45: =C45+B45 -> 24038 | E45: 25622 | F45: =E45+D45 -> 49660 | G45: =E45+C45 -> 37480 | H45: =(B45/2)+C45+E45 -> 43570 | I45: =F45*0.92 -> 45687.2 | J45: =H45*0.92 -> 40084.4 | K45: =+((B45/2)+C45+E45)*0.86 -> 37470.2 | L45: =+F45*0.86 -> 42707.6 | M45: =+F45-L45 -> 6952.4
A46: 2 | B46: 24360 | C46: 23716 | D46: =C46+B46 -> 48076 | E46: 25622 | F46: =E46+D46 -> 73698 | G46: =E46+C46 -> 49338 | H46: =(B46/2)+C46+E46 -> 61518 | I46: =F46*0.92 -> 67802.16 | J46: =H46*0.92 -> 56596.56 | K46: =+((B46/2)+C46+E46)*0.86 -> 52905.48 | L46: =+F46*0.86 -> 63380.28 | M46: =+F46-L46 -> 10317.72
A47: 3 | B47: 36540 | C47: 35574 | D47: =C47+B47 -> 72114 | E47: 25622 | F47: =E47+D47 -> 97736 | G47: =E47+C47 -> 61196 | H47: =(B47/2)+C47+E47 -> 79466 | I47: =F47*0.92 -> 89917.12 | J47: =H47*0.92 -> 73108.72 | K47: =+((B47/2)+C47+E47)*0.86 -> 68340.76 | L47: =+F47*0.86 -> 84052.96 | M47: =+F47-L47 -> 13683.04
A48: 4 | B48: 48720 | C48: 47432 | D48: =C48+B48 -> 96152 | E48: 25622 | F48: =E48+D48 -> 121774 | G48: =E48+C48 -> 73054 | H48: =(B48/2)+C48+E48 -> 97414 | I48: =F48*0.92 -> 112032.08 | J48: =H48*0.92 -> 89620.88 | K48: =+((B48/2)+C48+E48)*0.86 -> 83776.04 | L48: =+F48*0.86 -> 104725.64 | M48: =+F48-L48 -> 17048.36
A49: 5 | B49: 60899 | C49: 59289 | D49: =C49+B49 -> 120188 | E49: 25622 | F49: =E49+D49 -> 145810 | G49: =E49+C49 -> 84911 | H49: =(B49/2)+C49+E49 -> 115360.5 | I49: =F49*0.92 -> 134145.2 | J49: =H49*0.92 -> 106131.66 | K49: =+((B49/2)+C49+E49)*0.86 -> 99210.03 | L49: =+F49*0.86 -> 125396.6 | M49: =+F49-L49 -> 20413.4
A50: 6 | B50: 73079 | C50: 71147 | D50: =C50+B50 -> 144226 | E50: 25622 | F50: =E50+D50 -> 169848 | G50: =E50+C50 -> 96769 | H50: =(B50/2)+C50+E50 -> 133308.5 | I50: =F50*0.92 -> 156260.16 | J50: =H50*0.92 -> 122643.82 | K50: =+((B50/2)+C50+E50)*0.86 -> 114645.31 | L50: =+F50*0.86 -> 146069.28 | M50: =+F50-L50 -> 23778.72
A51: 7 | B51: 85259 | C51: 83005 | D51: =C51+B51 -> 168264 | E51: 25622 | F51: =E51+D51 -> 193886 | G51: =E51+C51 -> 108627 | H51: =(B51/2)+C51+E51 -> 151256.5 | I51: =F51*0.92 -> 178375.12 | J51: =H51*0.92 -> 139155.98 | K51: =+((B51/2)+C51+E51)*0.86 -> 130080.59 | L51: =+F51*0.86 -> 166741.96 | M51: =+F51-L51 -> 27144.04
A52: 8 | B52: 97439 | C52: 94863 | D52: =C52+B52 -> 192302 | E52: 25622 | F52: =E52+D52 -> 217924 | G52: =E52+C52 -> 120485 | H52: =(B52/2)+C52+E52 -> 169204.5 | I52: =F52*0.92 -> 200490.08 | J52: =H52*0.92 -> 155668.14 | K52: =+((B52/2)+C52+E52)*0.86 -> 145515.87 | L52: =+F52*0.86 -> 187414.64 | M52: =+F52-L52 -> 30509.36
A53: 9 | B53: 109619 | C53: 106721 | D53: =C53+B53 -> 216340 | E53: 25622 | F53: =E53+D53 -> 241962 | G53: =E53+C53 -> 132343 | H53: =(B53/2)+C53+E53 -> 187152.5 | I53: =F53*0.92 -> 222605.04 | J53: =H53*0.92 -> 172180.3 | K53: =+((B53/2)+C53+E53)*0.86 -> 160951.15 | L53: =+F53*0.86 -> 208087.32 | M53: =+F53-L53 -> 33874.68
A55: 50/50
A56: Units | B56: Total w/ SDA & OOA | C56: 50% SDA Scenario | D56: Landlord Guaranteed | E56: Excess Rev @ 50% SDA | F56: Excess Rev @ Full SDA | G56: Acares Share @ 50% SDA | H56: Acares Share @ 100% SDA | I56: Landlord Share
A57: 1 | B57: 49660 | C57: 43570 | D57: 140000 | G57: 0 | I57: =D57+(F57/2) -> 140000
A58: 2 | B58: 73698 | C58: 61518 | D58: 140000 | G58: 0 | I58: =D58+(F58/2) -> 140000
A59: 3 | B59: 97736 | C59: 79466 | D59: 140000 | G59: 0 | I59: =D59+(F59/2) -> 140000
A60: 4 | B60: 121774 | C60: 97414 | D60: 140000 | G60: 0 | I60: =D60+(F60/2) -> 140000
A61: 5 | B61: 145810 | C61: 115360.5 | D61: 140000 | F61: =+B61-D61 -> 5810 | G61: 0 | H61: =+F61/2 -> 2905 | I61: =D61+(F61/2) -> 142905
A62: 6 | B62: 169848 | C62: 133308.5 | D62: 140000 | F62: =+B62-D62 -> 29848 | G62: =C62-D62 -> -6691.5 | H62: =+F62/2 -> 14924 | I62: =D62+(F62/2) -> 154924
A63: 7 | B63: 193886 | C63: 151256.5 | D63: 140000 | E63: =+C63-D63 -> 11256.5 | F63: =+B63-D63 -> 53886 | G63: =(C63-D63)/2 -> 5628.25 | H63: =+F63/2 -> 26943 | I63: =D63+(F63/2) -> 166943
A64: 8 | B64: 217924 | C64: 169204.5 | D64: 140000 | E64: =+C64-D64 -> 29204.5 | F64: =+B64-D64 -> 77924 | G64: =(C64-D64)/2 -> 14602.25 | H64: =+F64/2 -> 38962 | I64: =D64+(F64/2) -> 178962
A65: 9 | B65: 241962 | C65: 187152.5 | D65: 140000 | E65: =+C65-D65 -> 47152.5 | F65: =+B65-D65 -> 101962 | G65: =(C65-D65)/2 -> 23576.25 | H65: =+F65/2 -> 50981 | I65: =D65+(F65/2) -> 190981
A68: 75/25 Split
A69: Units | B69: Total w/ SDA & OOA | C69: 50% SDA Scenario | D69: Landlord Guaranteed | E69: Excess Rev @ 50% SDA | F69: Excess Rev @ Full SDA | G69: Acares Share @ 50% SDA | H69: Acares Share @ 100% SDA | I69: Landlord Share
A70: 1 | B70: 49660 | C70: 43570 | D70: 140000 | G70: 0 | I70: =D70+(F70*0.25) -> 140000
A71: 2 | B71: 73698 | C71: 61518 | D71: 140000 | G71: 0 | I71: =D71+(F71*0.25) -> 140000
A72: 3 | B72: 97736 | C72: 79466 | D72: 140000 | G72: 0 | I72: =D72+(F72*0.25) -> 140000
A73: 4 | B73: 121774 | C73: 97414 | D73: 140000 | G73: 0 | I73: =D73+(F73*0.25) -> 140000
A74: 5 | B74: 145810 | C74: 115360.5 | D74: 140000 | F74: =+B74-D74 -> 5810 | G74: 0 | H74: =+F74*0.75 -> 4357.5 | I74: =D74+(F74*0.25) -> 141452.5
A75: 6 | B75: 169848 | C75: 133308.5 | D75: 140000 | F75: =+B75-D75 -> 29848 | G75: =C75-D75 -> -6691.5 | H75: =+F75*0.75 -> 22386 | I75: =D75+(F75*0.25) -> 147462
A76: 7 | B76: 193886 | C76: 151256.5 | D76: 140000 | E76: =+C76-D76 -> 11256.5 | F76: =+B76-D76 -> 53886 | G76: =(C76-D76)*0.75 -> 8442.375 | H76: =+F76*0.75 -> 40414.5 | I76: =D76+(F76*0.25) -> 153471.5
A77: 8 | B77: 217924 | C77: 169204.5 | D77: 140000 | E77: =+C77-D77 -> 29204.5 | F77: =+B77-D77 -> 77924 | G77: =(C77-D77)*0.75 -> 21903.375 | H77: =+F77*0.75 -> 58443 | I77: =D77+(F77*0.25) -> 159481
A78: 9 | B78: 241962 | C78: 187152.5 | D78: 140000 | E78: =+C78-D78 -> 47152.5 | F78: =+B78-D78 -> 101962 | G78: =(C78-D78)*0.75 -> 35364.375 | H78: =+F78*0.75 -> 76471.5 | I78: =D78+(F78*0.25) -> 165490.5
A81: 70/30
A82: Units | B82: Total w/ SDA & OOA | C82: 50% SDA Scenario | D82: Landlord Guaranteed | E82: Excess Rev @ 50% SDA | F82: Excess Rev @ Full SDA | G82: Acares Share @ 50% SDA | H82: Acares Share @ 100% SDA | I82: Landlord Share
A83: 1 | B83: 49660 | C83: 43570 | D83: 140000 | G83: 0 | I83: =D83+(F83*0.3) -> 140000
A84: 2 | B84: 73698 | C84: 61518 | D84: 140000 | G84: 0 | I84: =D84+(F84*0.3) -> 140000
A85: 3 | B85: 97736 | C85: 79466 | D85: 140000 | G85: 0 | I85: =D85+(F85*0.3) -> 140000
A86: 4 | B86: 121774 | C86: 97414 | D86: 140000 | G86: 0 | I86: =D86+(F86*0.3) -> 140000
A87: 5 | B87: 145810 | C87: 115360.5 | D87: 140000 | F87: =+B87-D87 -> 5810 | G87: 0 | H87: =+F87*0.75 -> 4357.5 | I87: =D87+(F87*0.3) -> 141743
A88: 6 | B88: 169848 | C88: 133308.5 | D88: 140000 | F88: =+B88-D88 -> 29848 | G88: 0 | H88: =+F88*0.7 -> 20893.6 | I88: =D88+(F88*0.3) -> 148954.4
A89: 7 | B89: 193886 | C89: 151256.5 | D89: 140000 | E89: =+C89-D89 -> 11256.5 | F89: =+B89-D89 -> 53886 | G89: =(C89-D89)*0.7 -> 7879.55 | H89: =+F89*0.7 -> 37720.2 | I89: =D89+(F89*0.3) -> 156165.8
A90: 8 | B90: 217924 | C90: 169204.5 | D90: 140000 | E90: =+C90-D90 -> 29204.5 | F90: =+B90-D90 -> 77924 | G90: =(C90-D90)*0.7 -> 20443.15 | H90: =+F90*0.7 -> 54546.8 | I90: =D90+(F90*0.3) -> 163377.2
A91: 9 | B91: 241962 | C91: 187152.5 | D91: 140000 | E91: =+C91-D91 -> 47152.5 | F91: =+B91-D91 -> 101962 | G91: =(C91-D91)*0.7 -> 33006.75 | H91: =+F91*0.7 -> 71373.4 | I91: =D91+(F91*0.3) -> 170588.6
A94: 60/40
A95: Units | B95: Total w/ SDA & OOA | C95: 50% SDA Scenario | D95: Landlord Guaranteed | E95: Excess Rev @ 50% SDA | F95: Excess Rev @ Full SDA | G95: Acares Share @ 50% SDA | H95: Acares Share @ 100% SDA | I95: Landlord Share
A96: 1 | B96: 49660 | C96: 43570 | D96: 140000 | G96: 0 | I96: =D96+(F96*0.4) -> 140000
A97: 2 | B97: 73698 | C97: 61518 | D97: 140000 | G97: 0 | I97: =D97+(F97*0.4) -> 140000
A98: 3 | B98: 97736 | C98: 79466 | D98: 140000 | G98: 0 | I98: =D98+(F98*0.4) -> 140000
A99: 4 | B99: 121774 | C99: 97414 | D99: 140000 | G99: 0 | I99: =D99+(F99*0.4) -> 140000
A100: 5 | B100: 145810 | C100: 115360.5 | D100: 140000 | F100: =+B100-D100 -> 5810 | G100: 0 | H100: =+F100*0.6 -> 3486 | I100: =D100+(F100*0.4) -> 142324
A101: 6 | B101: 169848 | C101: 133308.5 | D101: 140000 | F101: =+B101-D101 -> 29848 | G101: 0 | H101: =+F101*0.6 -> 17908.8 | I101: =D101+(F101*0.4) -> 151939.2
A102: 7 | B102: 193886 | C102: 151256.5 | D102: 140000 | E102: =+C102-D102 -> 11256.5 | F102: =+B102-D102 -> 53886 | G102: =(C102-D102)*0.6 -> 6753.9 | H102: =+F102*0.6 -> 32331.6 | I102: =D102+(F102*0.4) -> 161554.4
A103: 8 | B103: 217924 | C103: 169204.5 | D103: 140000 | E103: =+C103-D103 -> 29204.5 | F103: =+B103-D103 -> 77924 | G103: =(C103-D103)*0.6 -> 17522.7 | H103: =+F103*0.6 -> 46754.4 | I103: =D103+(F103*0.4) -> 171169.6
A104: 9 | B104: 241962 | C104: 187152.5 | D104: 140000 | E104: =+C104-D104 -> 47152.5 | F104: =+B104-D104 -> 101962 | G104: =(C104-D104)*0.6 -> 28291.5 | H104: =+F104*0.6 -> 61177.2 | I104: =D104+(F104*0.4) -> 180784.8
A108: Current
A109: Units | B109: SDA Basic | C109: RRC | D109: SDA + RRC | E109: OOA Lease | F109: Total w/ SDA | G109: Total w/o SDA | H109: 50% SDA Scenario | I109: Landlord Share (92%) Full SDA | J109: Landlord Share (92%) @ 50% SDA | K109: No SDA Landlord @ 8% | L109: Maintainance (15%) | M109: Rates | N109: Insurance | O109: xxxx | P109: Total Expenses Ex interest | Q109: Net cash flow before interest | R109: Interest | S109: Net Cashflow
A110: 1 | C110: 11858 | E110: 25622 | G110: =E110+C110 -> 37480 | H110: =(B110/2)+C110+E110 -> 37480 | I110: =F110*0.92 -> 0 | J110: =H110*0.92 -> 34481.6 | K110: =G110*0.92 -> 34481.6 | L110: =+G110*0.15 -> 5622 | M110: =1270*10 -> 12700 | N110: 12000 | P110: =SUM(L110:O110) -> 30322 | Q110: =+K110-P110 -> 4159.6
A111: 2 | C111: 23716 | E111: 25622 | G111: =E111+C111 -> 49338 | H111: =(B111/2)+C111+E111 -> 49338 | I111: =F111*0.92 -> 0 | J111: =H111*0.92 -> 45390.96 | K111: =G111*0.92 -> 45390.96 | L111: =+G111*0.15 -> 7400.7 | M111: =1270*10 -> 12700 | N111: 12000 | P111: =SUM(L111:O111) -> 32100.7 | Q111: =+K111-P111 -> 13290.26
A112: 3 | C112: 35574 | E112: 25622 | G112: =E112+C112 -> 61196 | H112: =(B112/2)+C112+E112 -> 61196 | I112: =F112*0.92 -> 0 | J112: =H112*0.92 -> 56300.32 | K112: =G112*0.92 -> 56300.32 | L112: =+G112*0.15 -> 9179.4 | M112: =1270*10 -> 12700 | N112: 12000 | P112: =SUM(L112:O112) -> 33879.4 | Q112: =+K112-P112 -> 22420.92
A113: 4 | C113: 47432 | E113: 25622 | G113: =E113+C113 -> 73054 | H113: =(B113/2)+C113+E113 -> 73054 | I113: =F113*0.92 -> 0 | J113: =H113*0.92 -> 67209.68 | K113: =G113*0.92 -> 67209.68 | L113: =+G113*0.15 -> 10958.1 | M113: =1270*10 -> 12700 | N113: 12000 | P113: =SUM(L113:O113) -> 35658.1 | Q113: =+K113-P113 -> 31551.58 | R113: 118000 | S113: =+Q113-R113 -> -86448.42
A114: 5 | C114: 59289 | E114: 25622 | G114: =E114+C114 -> 84911 | H114: =(B114/2)+C114+E114 -> 84911 | I114: =F114*0.92 -> 0 | J114: =H114*0.92 -> 78118.12 | K114: =G114*0.92 -> 78118.12 | L114: =+G114*0.15 -> 12736.65 | M114: =1270*10 -> 12700 | N114: 12000 | P114: =SUM(L114:O114) -> 37436.65 | Q114: =+K114-P114 -> 40681.47 | R114: 118000 | S114: =+Q114-R114 -> -77318.53
A115: 6 | C115: 71147 | E115: 25622 | G115: =E115+C115 -> 96769 | H115: =(B115/2)+C115+E115 -> 96769 | I115: =F115*0.92 -> 0 | J115: =H115*0.92 -> 89027.48 | K115: =G115*0.92 -> 89027.48 | L115: =+G115*0.15 -> 14515.35 | M115: =1270*10 -> 12700 | N115: 12000 | P115: =SUM(L115:O115) -> 39215.35 | Q115: =+K115-P115 -> 49812.13 | R115: 118000 | S115: =+Q115-R115 -> -68187.87
A116: 7 | C116: 83005 | E116: 25622 | G116: =E116+C116 -> 108627 | H116: =(B116/2)+C116+E116 -> 108627 | I116: =F116*0.92 -> 0 | J116: =H116*0.92 -> 99936.84 | K116: =G116*0.92 -> 99936.84 | L116: =+G116*0.15 -> 16294.05 | M116: =1270*10 -> 12700 | N116: 12000 | P116: =SUM(L116:O116) -> 40994.05 | Q116: =+K116-P116 -> 58942.79 | R116: 118000 | S116: =+Q116-R116 -> -59057.21
...
